Workbook

Sheet Dashboard
A1: CodeCritters Inc. - Trial Balance Comparison Dashboard
A2: PythonMuse LLC | Training & Demo Template
A4: Materiality Thresholds
A5: Comparison | B5: $ Threshold | C5: % Threshold
A6: Year-over-Year | B6: 2500 | C6: 0.15
A7: Month-over-Month | B7: 2500 | C7: 0.2
A9: Flag Counts
A10: YoY flags | B10: =COUNTIF(YoY_Variance!I3:I10000,"FLAG")
A11: MoM flags | B11: =COUNTIF(MoM_Variance!J3:J10000,"FLAG")
A13: Reconciliation Check (Assets = Liabilities + Equity, net of contras)
A14: Year | B14: Month | C14: Assets (net) | D14: Liabilities + Equity (net) | E14: Diff | F14: Status
A15: 2025 | B15: Jan | C15: =SUMIF('TB_2025'!$C$3:$C$34,"Asset",'TB_2025'!$D$3:$D$34)-SUMIF('TB_2025'!$B$3:$B$34,"Accumulated Depreciation",'TB_2025'!$D$3:$D$34)*2 | D15: =SUMIF('TB_2025'!$C$3:$C$34,"Liability",'TB_2025'!$D$3:$D$34)+SUMIF('TB_2025'!$C$3:$C$34,"Equity",'TB_2025'!$D$3:$D$34)-SUMIF('TB_2025'!$B$3:$B$34,"Owner Draws",'TB_2025'!$D$3:$D$34)*2 | E15: =C15-D15 | F15: =IF(ROUND(E15,2)=0,"OK","MISMATCH")
A16: 2025 | B16: Feb | C16: =SUMIF('TB_2025'!$C$3:$C$34,"Asset",'TB_2025'!$E$3:$E$34)-SUMIF('TB_2025'!$B$3:$B$34,"Accumulated Depreciation",'TB_2025'!$E$3:$E$34)*2 | D16: =SUMIF('TB_2025'!$C$3:$C$34,"Liability",'TB_2025'!$E$3:$E$34)+SUMIF('TB_2025'!$C$3:$C$34,"Equity",'TB_2025'!$E$3:$E$34)-SUMIF('TB_2025'!$B$3:$B$34,"Owner Draws",'TB_2025'!$E$3:$E$34)*2 | E16: =C16-D16 | F16: =IF(ROUND(E16,2)=0,"OK","MISMATCH")
A17: 2025 | B17: Mar | C17: =SUMIF('TB_2025'!$C$3:$C$34,"Asset",'TB_2025'!$F$3:$F$34)-SUMIF('TB_2025'!$B$3:$B$34,"Accumulated Depreciation",'TB_2025'!$F$3:$F$34)*2 | D17: =SUMIF('TB_2025'!$C$3:$C$34,"Liability",'TB_2025'!$F$3:$F$34)+SUMIF('TB_2025'!$C$3:$C$34,"Equity",'TB_2025'!$F$3:$F$34)-SUMIF('TB_2025'!$B$3:$B$34,"Owner Draws",'TB_2025'!$F$3:$F$34)*2 | E17: =C17-D17 | F17: =IF(ROUND(E17,2)=0,"OK","MISMATCH")
A18: 2025 | B18: Apr | C18: =SUMIF('TB_2025'!$C$3:$C$34,"Asset",'TB_2025'!$G$3:$G$34)-SUMIF('TB_2025'!$B$3:$B$34,"Accumulated Depreciation",'TB_2025'!$G$3:$G$34)*2 | D18: =SUMIF('TB_2025'!$C$3:$C$34,"Liability",'TB_2025'!$G$3:$G$34)+SUMIF('TB_2025'!$C$3:$C$34,"Equity",'TB_2025'!$G$3:$G$34)-SUMIF('TB_2025'!$B$3:$B$34,"Owner Draws",'TB_2025'!$G$3:$G$34)*2 | E18: =C18-D18 | F18: =IF(ROUND(E18,2)=0,"OK","MISMATCH")
A19: 2026 | B19: Jan | C19: =SUMIF('TB_2026'!$C$3:$C$34,"Asset",'TB_2026'!$D$3:$D$34)-SUMIF('TB_2026'!$B$3:$B$34,"Accumulated Depreciation",'TB_2026'!$D$3:$D$34)*2 | D19: =SUMIF('TB_2026'!$C$3:$C$34,"Liability",'TB_2026'!$D$3:$D$34)+SUMIF('TB_2026'!$C$3:$C$34,"Equity",'TB_2026'!$D$3:$D$34)-SUMIF('TB_2026'!$B$3:$B$34,"Owner Draws",'TB_2026'!$D$3:$D$34)*2 | E19: =C19-D19 | F19: =IF(ROUND(E19,2)=0,"OK","MISMATCH")
A20: 2026 | B20: Feb | C20: =SUMIF('TB_2026'!$C$3:$C$34,"Asset",'TB_2026'!$E$3:$E$34)-SUMIF('TB_2026'!$B$3:$B$34,"Accumulated Depreciation",'TB_2026'!$E$3:$E$34)*2 | D20: =SUMIF('TB_2026'!$C$3:$C$34,"Liability",'TB_2026'!$E$3:$E$34)+SUMIF('TB_2026'!$C$3:$C$34,"Equity",'TB_2026'!$E$3:$E$34)-SUMIF('TB_2026'!$B$3:$B$34,"Owner Draws",'TB_2026'!$E$3:$E$34)*2 | E20: =C20-D20 | F20: =IF(ROUND(E20,2)=0,"OK","MISMATCH")
A21: 2026 | B21: Mar | C21: =SUMIF('TB_2026'!$C$3:$C$34,"Asset",'TB_2026'!$F$3:$F$34)-SUMIF('TB_2026'!$B$3:$B$34,"Accumulated Depreciation",'TB_2026'!$F$3:$F$34)*2 | D21: =SUMIF('TB_2026'!$C$3:$C$34,"Liability",'TB_2026'!$F$3:$F$34)+SUMIF('TB_2026'!$C$3:$C$34,"Equity",'TB_2026'!$F$3:$F$34)-SUMIF('TB_2026'!$B$3:$B$34,"Owner Draws",'TB_2026'!$F$3:$F$34)*2 | E21: =C21-D21 | F21: =IF(ROUND(E21,2)=0,"OK","MISMATCH")
A22: 2026 | B22: Apr | C22: =SUMIF('TB_2026'!$C$3:$C$34,"Asset",'TB_2026'!$G$3:$G$34)-SUMIF('TB_2026'!$B$3:$B$34,"Accumulated Depreciation",'TB_2026'!$G$3:$G$34)*2 | D22: =SUMIF('TB_2026'!$C$3:$C$34,"Liability",'TB_2026'!$G$3:$G$34)+SUMIF('TB_2026'!$C$3:$C$34,"Equity",'TB_2026'!$G$3:$G$34)-SUMIF('TB_2026'!$B$3:$B$34,"Owner Draws",'TB_2026'!$G$3:$G$34)*2 | E22: =C22-D22 | F22: =IF(ROUND(E22,2)=0,"OK","MISMATCH")

Sheet TB_2025
A1: Trial Balance - 2025 (Prior Year) (source data, do not edit)
A2: Account Code | B2: Account | C2: Type | D2: Jan | E2: Feb | F2: Mar | G2: Apr
A3: 1000 | B3: Checking | C3: Asset | D3: 7600 | E3: 11270 | F3: 18855 | G3: 27430
A4: 1010 | B4: Savings | C4: Asset | D4: 20000 | E4: 20000 | F4: 20000 | G4: 20000
A5: 1200 | B5: Accounts Receivable | C5: Asset | D5: 14000 | E5: 14500 | F5: 15000 | G5: 15200
A6: 1300 | B6: Inventory - Raw Materials | C6: Asset | D6: 8000 | E6: 8200 | F6: 8400 | G6: 8600
A7: 1310 | B7: Inventory - Finished Goods | C7: Asset | D7: 11000 | E7: 11200 | F7: 11400 | G7: 11600
A8: 1400 | B8: Prepaid Insurance | C8: Asset | D8: 2400 | E8: 2200 | F8: 2000 | G8: 1800
A9: 1500 | B9: Equipment | C9: Asset | D9: 45000 | E9: 45000 | F9: 45000 | G9: 45000
A10: 1510 | B10: Accumulated Depreciation | C10: Asset | D10: 9800 | E10: 10600 | F10: 11400 | G10: 12200
A11: 2000 | B11: Accounts Payable | C11: Liability | D11: 7000 | E11: 7200 | F11: 7400 | G11: 7600
A12: 2100 | B12: Credit Card Payable | C12: Liability | D12: 3200 | E12: 3300 | F12: 3100 | G12: 3400
A13: 2200 | B13: Sales Tax Payable | C13: Liability | D13: 1800 | E13: 1850 | F13: 1900 | G13: 1950
A14: 2300 | B14: Payroll Liabilities | C14: Liability | D14: 2200 | E14: 2200 | F14: 2300 | G14: 2300
... A34: 6090 | B34: Office Supplies | C34: Expense | D34: 150 | E34: 140 | F34: 160 | G34: 155

Sheet TB_2026
A1: Trial Balance - 2026 (Current Year) (source data, do not edit)
A2: Account Code | B2: Account | C2: Type | D2: Jan | E2: Feb | F2: Mar | G2: Apr
A3: 1000 | B3: Checking | C3: Asset | D3: 42870 | E3: 47175 | F3: 41325 | G3: 41385
A4: 1010 | B4: Savings | C4: Asset | D4: 20000 | E4: 20000 | F4: 20000 | G4: 20000
A5: 1200 | B5: Accounts Receivable | C5: Asset | D5: 15400 | E5: 15700 | F5: 16100 | G5: 24800
A6: 1300 | B6: Inventory - Raw Materials | C6: Asset | D6: 8700 | E6: 8850 | F6: 9200 | G6: 9500
A7: 1310 | B7: Inventory - Finished Goods | C7: Asset | D7: 11700 | E7: 11900 | F7: 12100 | G7: 12300
A8: 1400 | B8: Prepaid Insurance | C8: Asset | D8: 1600 | E8: 1400 | F8: 1200 | G8: 1000
A9: 1500 | B9: Equipment | C9: Asset | D9: 45000 | E9: 45000 | F9: 46800 | G9: 46800
A10: 1510 | B10: Accumulated Depreciation | C10: Asset | D10: 13000 | E10: 13800 | F10: 14600 | G10: 15400
A11: 2000 | B11: Accounts Payable | C11: Liability | D11: 7700 | E11: 7900 | F11: 8100 | G11: 8300
A12: 2100 | B12: Credit Card Payable | C12: Liability | D12: 3500 | E12: 3600 | F12: 3450 | G12: 4700
A13: 2200 | B13: Sales Tax Payable | C13: Liability | D13: 1980 | E13: 2020 | F13: 2060 | G13: 2100
A14: 2300 | B14: Payroll Liabilities | C14: Liability | D14: 2350 | E14: 2350 | F14: 2400 | G14: 2400
... A34: 6090 | B34: Office Supplies | C34: Expense | D34: 160 | E34: 150 | F34: 900 | G34: 170

Sheet YoY_Variance
A1: Year-over-Year Variance - same month, 2026 vs. 2025
A2: Account Code | B2: Account | C2: Type | D2: Month | E2: Prior (2025) | F2: Current (2026) | G2: $ Var | H2: % Var | I2: Flag
A3: ='TB_2025'!A3 | B3: ='TB_2025'!B3 | C3: ='TB_2025'!C3 | D3: Jan | E3: ='TB_2025'!D3 | F3: ='TB_2026'!D3 | G3: =F3-E3 | H3: =IF(E3=0,"",G3/ABS(E3)) | I3: =IF(AND(ABS(G3)>Dashboard!$B$6,ISNUMBER(H3),ABS(H3)>Dashboard!$C$6),"FLAG","")
A4: ='TB_2025'!A3 | B4: ='TB_2025'!B3 | C4: ='TB_2025'!C3 | D4: Feb | E4: ='TB_2025'!E3 | F4: ='TB_2026'!E3 | G4: =F4-E4 | H4: =IF(E4=0,"",G4/ABS(E4)) | I4: =IF(AND(ABS(G4)>Dashboard!$B$6,ISNUMBER(H4),ABS(H4)>Dashboard!$C$6),"FLAG","")
A5: ='TB_2025'!A3 | B5: ='TB_2025'!B3 | C5: ='TB_2025'!C3 | D5: Mar | E5: ='TB_2025'!F3 | F5: ='TB_2026'!F3 | G5: =F5-E5 | H5: =IF(E5=0,"",G5/ABS(E5)) | I5: =IF(AND(ABS(G5)>Dashboard!$B$6,ISNUMBER(H5),ABS(H5)>Dashboard!$C$6),"FLAG","")
A6: ='TB_2025'!A3 | B6: ='TB_2025'!B3 | C6: ='TB_2025'!C3 | D6: Apr | E6: ='TB_2025'!G3 | F6: ='TB_2026'!G3 | G6: =F6-E6 | H6: =IF(E6=0,"",G6/ABS(E6)) | I6: =IF(AND(ABS(G6)>Dashboard!$B$6,ISNUMBER(H6),ABS(H6)>Dashboard!$C$6),"FLAG","")
A7: ='TB_2025'!A4 | B7: ='TB_2025'!B4 | C7: ='TB_2025'!C4 | D7: Jan | E7: ='TB_2025'!D4 | F7: ='TB_2026'!D4 | G7: =F7-E7 | H7: =IF(E7=0,"",G7/ABS(E7)) | I7: =IF(AND(ABS(G7)>Dashboard!$B$6,ISNUMBER(H7),ABS(H7)>Dashboard!$C$6),"FLAG","")
A8: ='TB_2025'!A4 | B8: ='TB_2025'!B4 | C8: ='TB_2025'!C4 | D8: Feb | E8: ='TB_2025'!E4 | F8: ='TB_2026'!E4 | G8: =F8-E8 | H8: =IF(E8=0,"",G8/ABS(E8)) | I8: =IF(AND(ABS(G8)>Dashboard!$B$6,ISNUMBER(H8),ABS(H8)>Dashboard!$C$6),"FLAG","")
A9: ='TB_2025'!A4 | B9: ='TB_2025'!B4 | C9: ='TB_2025'!C4 | D9: Mar | E9: ='TB_2025'!F4 | F9: ='TB_2026'!F4 | G9: =F9-E9 | H9: =IF(E9=0,"",G9/ABS(E9)) | I9: =IF(AND(ABS(G9)>Dashboard!$B$6,ISNUMBER(H9),ABS(H9)>Dashboard!$C$6),"FLAG","")
A10: ='TB_2025'!A4 | B10: ='TB_2025'!B4 | C10: ='TB_2025'!C4 | D10: Apr | E10: ='TB_2025'!G4 | F10: ='TB_2026'!G4 | G10: =F10-E10 | H10: =IF(E10=0,"",G10/ABS(E10)) | I10: =IF(AND(ABS(G10)>Dashboard!$B$6,ISNUMBER(H10),ABS(H10)>Dashboard!$C$6),"FLAG","")
A11: ='TB_2025'!A5 | B11: ='TB_2025'!B5 | C11: ='TB_2025'!C5 | D11: Jan | E11: ='TB_2025'!D5 | F11: ='TB_2026'!D5 | G11: =F11-E11 | H11: =IF(E11=0,"",G11/ABS(E11)) | I11: =IF(AND(ABS(G11)>Dashboard!$B$6,ISNUMBER(H11),ABS(H11)>Dashboard!$C$6),"FLAG","")
A12: ='TB_2025'!A5 | B12: ='TB_2025'!B5 | C12: ='TB_2025'!C5 | D12: Feb | E12: ='TB_2025'!E5 | F12: ='TB_2026'!E5 | G12: =F12-E12 | H12: =IF(E12=0,"",G12/ABS(E12)) | I12: =IF(AND(ABS(G12)>Dashboard!$B$6,ISNUMBER(H12),ABS(H12)>Dashboard!$C$6),"FLAG","")
A13: ='TB_2025'!A5 | B13: ='TB_2025'!B5 | C13: ='TB_2025'!C5 | D13: Mar | E13: ='TB_2025'!F5 | F13: ='TB_2026'!F5 | G13: =F13-E13 | H13: =IF(E13=0,"",G13/ABS(E13)) | I13: =IF(AND(ABS(G13)>Dashboard!$B$6,ISNUMBER(H13),ABS(H13)>Dashboard!$C$6),"FLAG","")
A14: ='TB_2025'!A5 | B14: ='TB_2025'!B5 | C14: ='TB_2025'!C5 | D14: Apr | E14: ='TB_2025'!G5 | F14: ='TB_2026'!G5 | G14: =F14-E14 | H14: =IF(E14=0,"",G14/ABS(E14)) | I14: =IF(AND(ABS(G14)>Dashboard!$B$6,ISNUMBER(H14),ABS(H14)>Dashboard!$C$6),"FLAG","")
A15: ='TB_2025'!A6 | B15: ='TB_2025'!B6 | C15: ='TB_2025'!C6 | D15: Jan | E15: ='TB_2025'!D6 | F15: ='TB_2026'!D6 | G15: =F15-E15 | H15: =IF(E15=0,"",G15/ABS(E15)) | I15: =IF(AND(ABS(G15)>Dashboard!$B$6,ISNUMBER(H15),ABS(H15)>Dashboard!$C$6),"FLAG","")
A16: ='TB_2025'!A6 | B16: ='TB_2025'!B6 | C16: ='TB_2025'!C6 | D16: Feb | E16: ='TB_2025'!E6 | F16: ='TB_2026'!E6 | G16: =F16-E16 | H16: =IF(E16=0,"",G16/ABS(E16)) | I16: =IF(AND(ABS(G16)>Dashboard!$B$6,ISNUMBER(H16),ABS(H16)>Dashboard!$C$6),"FLAG","")
A17: ='TB_2025'!A6 | B17: ='TB_2025'!B6 | C17: ='TB_2025'!C6 | D17: Mar | E17: ='TB_2025'!F6 | F17: ='TB_2026'!F6 | G17: =F17-E17 | H17: =IF(E17=0,"",G17/ABS(E17)) | I17: =IF(AND(ABS(G17)>Dashboard!$B$6,ISNUMBER(H17),ABS(H17)>Dashboard!$C$6),"FLAG","")
A18: ='TB_2025'!A6 | B18: ='TB_2025'!B6 | C18: ='TB_2025'!C6 | D18: Apr | E18: ='TB_2025'!G6 | F18: ='TB_2026'!G6 | G18: =F18-E18 | H18: =IF(E18=0,"",G18/ABS(E18)) | I18: =IF(AND(ABS(G18)>Dashboard!$B$6,ISNUMBER(H18),ABS(H18)>Dashboard!$C$6),"FLAG","")
A19: ='TB_2025'!A7 | B19: ='TB_2025'!B7 | C19: ='TB_2025'!C7 | D19: Jan | E19: ='TB_2025'!D7 | F19: ='TB_2026'!D7 | G19: =F19-E19 | H19: =IF(E19=0,"",G19/ABS(E19)) | I19: =IF(AND(ABS(G19)>Dashboard!$B$6,ISNUMBER(H19),ABS(H19)>Dashboard!$C$6),"FLAG","")
A20: ='TB_2025'!A7 | B20: ='TB_2025'!B7 | C20: ='TB_2025'!C7 | D20: Feb | E20: ='TB_2025'!E7 | F20: ='TB_2026'!E7 | G20: =F20-E20 | H20: =IF(E20=0,"",G20/ABS(E20)) | I20: =IF(AND(ABS(G20)>Dashboard!$B$6,ISNUMBER(H20),ABS(H20)>Dashboard!$C$6),"FLAG","")
A21: ='TB_2025'!A7 | B21: ='TB_2025'!B7 | C21: ='TB_2025'!C7 | D21: Mar | E21: ='TB_2025'!F7 | F21: ='TB_2026'!F7 | G21: =F21-E21 | H21: =IF(E21=0,"",G21/ABS(E21)) | I21: =IF(AND(ABS(G21)>Dashboard!$B$6,ISNUMBER(H21),ABS(H21)>Dashboard!$C$6),"FLAG","")
A22: ='TB_2025'!A7 | B22: ='TB_2025'!B7 | C22: ='TB_2025'!C7 | D22: Apr | E22: ='TB_2025'!G7 | F22: ='TB_2026'!G7 | G22: =F22-E22 | H22: =IF(E22=0,"",G22/ABS(E22)) | I22: =IF(AND(ABS(G22)>Dashboard!$B$6,ISNUMBER(H22),ABS(H22)>Dashboard!$C$6),"FLAG","")
A23: ='TB_2025'!A8 | B23: ='TB_2025'!B8 | C23: ='TB_2025'!C8 | D23: Jan | E23: ='TB_2025'!D8 | F23: ='TB_2026'!D8 | G23: =F23-E23 | H23: =IF(E23=0,"",G23/ABS(E23)) | I23: =IF(AND(ABS(G23)>Dashboard!$B$6,ISNUMBER(H23),ABS(H23)>Dashboard!$C$6),"FLAG","")
A24: ='TB_2025'!A8 | B24: ='TB_2025'!B8 | C24: ='TB_2025'!C8 | D24: Feb | E24: ='TB_2025'!E8 | F24: ='TB_2026'!E8 | G24: =F24-E24 | H24: =IF(E24=0,"",G24/ABS(E24)) | I24: =IF(AND(ABS(G24)>Dashboard!$B$6,ISNUMBER(H24),ABS(H24)>Dashboard!$C$6),"FLAG","")
A25: ='TB_2025'!A8 | B25: ='TB_2025'!B8 | C25: ='TB_2025'!C8 | D25: Mar | E25: ='TB_2025'!F8 | F25: ='TB_2026'!F8 | G25: =F25-E25 | H25: =IF(E25=0,"",G25/ABS(E25)) | I25: =IF(AND(ABS(G25)>Dashboard!$B$6,ISNUMBER(H25),ABS(H25)>Dashboard!$C$6),"FLAG","")
A26: ='TB_2025'!A8 | B26: ='TB_2025'!B8 | C26: ='TB_2025'!C8 | D26: Apr | E26: ='TB_2025'!G8 | F26: ='TB_2026'!G8 | G26: =F26-E26 | H26: =IF(E26=0,"",G26/ABS(E26)) | I26: =IF(AND(ABS(G26)>Dashboard!$B$6,ISNUMBER(H26),ABS(H26)>Dashboard!$C$6),"FLAG","")
A27: ='TB_2025'!A9 | B27: ='TB_2025'!B9 | C27: ='TB_2025'!C9 | D27: Jan | E27: ='TB_2025'!D9 | F27: ='TB_2026'!D9 | G27: =F27-E27 | H27: =IF(E27=0,"",G27/ABS(E27)) | I27: =IF(AND(ABS(G27)>Dashboard!$B$6,ISNUMBER(H27),ABS(H27)>Dashboard!$C$6),"FLAG","")
A28: ='TB_2025'!A9 | B28: ='TB_2025'!B9 | C28: ='TB_2025'!C9 | D28: Feb | E28: ='TB_2025'!E9 | F28: ='TB_2026'!E9 | G28: =F28-E28 | H28: =IF(E28=0,"",G28/ABS(E28)) | I28: =IF(AND(ABS(G28)>Dashboard!$B$6,ISNUMBER(H28),ABS(H28)>Dashboard!$C$6),"FLAG","")
A29: ='TB_2025'!A9 | B29: ='TB_2025'!B9 | C29: ='TB_2025'!C9 | D29: Mar | E29: ='TB_2025'!F9 | F29: ='TB_2026'!F9 | G29: =F29-E29 | H29: =IF(E29=0,"",G29/ABS(E29)) | I29: =IF(AND(ABS(G29)>Dashboard!$B$6,ISNUMBER(H29),ABS(H29)>Dashboard!$C$6),"FLAG","")
A30: ='TB_2025'!A9 | B30: ='TB_2025'!B9 | C30: ='TB_2025'!C9 | D30: Apr | E30: ='TB_2025'!G9 | F30: ='TB_2026'!G9 | G30: =F30-E30 | H30: =IF(E30=0,"",G30/ABS(E30)) | I30: =IF(AND(ABS(G30)>Dashboard!$B$6,ISNUMBER(H30),ABS(H30)>Dashboard!$C$6),"FLAG","")
A31: ='TB_2025'!A10 | B31: ='TB_2025'!B10 | C31: ='TB_2025'!C10 | D31: Jan | E31: ='TB_2025'!D10 | F31: ='TB_2026'!D10 | G31: =F31-E31 | H31: =IF(E31=0,"",G31/ABS(E31)) | I31: =IF(AND(ABS(G31)>Dashboard!$B$6,ISNUMBER(H31),ABS(H31)>Dashboard!$C$6),"FLAG","")
A32: ='TB_2025'!A10 | B32: ='TB_2025'!B10 | C32: ='TB_2025'!C10 | D32: Feb | E32: ='TB_2025'!E10 | F32: ='TB_2026'!E10 | G32: =F32-E32 | H32: =IF(E32=0,"",G32/ABS(E32)) | I32: =IF(AND(ABS(G32)>Dashboard!$B$6,ISNUMBER(H32),ABS(H32)>Dashboard!$C$6),"FLAG","")
A33: ='TB_2025'!A10 | B33: ='TB_2025'!B10 | C33: ='TB_2025'!C10 | D33: Mar | E33: ='TB_2025'!F10 | F33: ='TB_2026'!F10 | G33: =F33-E33 | H33: =IF(E33=0,"",G33/ABS(E33)) | I33: =IF(AND(ABS(G33)>Dashboard!$B$6,ISNUMBER(H33),ABS(H33)>Dashboard!$C$6),"FLAG","")
A34: ='TB_2025'!A10 | B34: ='TB_2025'!B10 | C34: ='TB_2025'!C10 | D34: Apr | E34: ='TB_2025'!G10 | F34: ='TB_2026'!G10 | G34: =F34-E34 | H34: =IF(E34=0,"",G34/ABS(E34)) | I34: =IF(AND(ABS(G34)>Dashboard!$B$6,ISNUMBER(H34),ABS(H34)>Dashboard!$C$6),"FLAG","")
A35: ='TB_2025'!A11 | B35: ='TB_2025'!B11 | C35: ='TB_2025'!C11 | D35: Jan | E35: ='TB_2025'!D11 | F35: ='TB_2026'!D11 | G35: =F35-E35 | H35: =IF(E35=0,"",G35/ABS(E35)) | I35: =IF(AND(ABS(G35)>Dashboard!$B$6,ISNUMBER(H35),ABS(H35)>Dashboard!$C$6),"FLAG","")
A36: ='TB_2025'!A11 | B36: ='TB_2025'!B11 | C36: ='TB_2025'!C11 | D36: Feb | E36: ='TB_2025'!E11 | F36: ='TB_2026'!E11 | G36: =F36-E36 | H36: =IF(E36=0,"",G36/ABS(E36)) | I36: =IF(AND(ABS(G36)>Dashboard!$B$6,ISNUMBER(H36),ABS(H36)>Dashboard!$C$6),"FLAG","")
A37: ='TB_2025'!A11 | B37: ='TB_2025'!B11 | C37: ='TB_2025'!C11 | D37: Mar | E37: ='TB_2025'!F11 | F37: ='TB_2026'!F11 | G37: =F37-E37 | H37: =IF(E37=0,"",G37/ABS(E37)) | I37: =IF(AND(ABS(G37)>Dashboard!$B$6,ISNUMBER(H37),ABS(H37)>Dashboard!$C$6),"FLAG","")
A38: ='TB_2025'!A11 | B38: ='TB_2025'!B11 | C38: ='TB_2025'!C11 | D38: Apr | E38: ='TB_2025'!G11 | F38: ='TB_2026'!G11 | G38: =F38-E38 | H38: =IF(E38=0,"",G38/ABS(E38)) | I38: =IF(AND(ABS(G38)>Dashboard!$B$6,ISNUMBER(H38),ABS(H38)>Dashboard!$C$6),"FLAG","")
A39: ='TB_2025'!A12 | B39: ='TB_2025'!B12 | C39: ='TB_2025'!C12 | D39: Jan | E39: ='TB_2025'!D12 | F39: ='TB_2026'!D12 | G39: =F39-E39 | H39: =IF(E39=0,"",G39/ABS(E39)) | I39: =IF(AND(ABS(G39)>Dashboard!$B$6,ISNUMBER(H39),ABS(H39)>Dashboard!$C$6),"FLAG","")
A40: ='TB_2025'!A12 | B40: ='TB_2025'!B12 | C40: ='TB_2025'!C12 | D40: Feb | E40: ='TB_2025'!E12 | F40: ='TB_2026'!E12 | G40: =F40-E40 | H40: =IF(E40=0,"",G40/ABS(E40)) | I40: =IF(AND(ABS(G40)>Dashboard!$B$6,ISNUMBER(H40),ABS(H40)>Dashboard!$C$6),"FLAG","")
A41: ='TB_2025'!A12 | B41: ='TB_2025'!B12 | C41: ='TB_2025'!C12 | D41: Mar | E41: ='TB_2025'!F12 | F41: ='TB_2026'!F12 | G41: =F41-E41 | H41: =IF(E41=0,"",G41/ABS(E41)) | I41: =IF(AND(ABS(G41)>Dashboard!$B$6,ISNUMBER(H41),ABS(H41)>Dashboard!$C$6),"FLAG","")
A42: ='TB_2025'!A12 | B42: ='TB_2025'!B12 | C42: ='TB_2025'!C12 | D42: Apr | E42: ='TB_2025'!G12 | F42: ='TB_2026'!G12 | G42: =F42-E42 | H42: =IF(E42=0,"",G42/ABS(E42)) | I42: =IF(AND(ABS(G42)>Dashboard!$B$6,ISNUMBER(H42),ABS(H42)>Dashboard!$C$6),"FLAG","")
A43: ='TB_2025'!A13 | B43: ='TB_2025'!B13 | C43: ='TB_2025'!C13 | D43: Jan | E43: ='TB_2025'!D13 | F43: ='TB_2026'!D13 | G43: =F43-E43 | H43: =IF(E43=0,"",G43/ABS(E43)) | I43: =IF(AND(ABS(G43)>Dashboard!$B$6,ISNUMBER(H43),ABS(H43)>Dashboard!$C$6),"FLAG","")
A44: ='TB_2025'!A13 | B44: ='TB_2025'!B13 | C44: ='TB_2025'!C13 | D44: Feb | E44: ='TB_2025'!E13 | F44: ='TB_2026'!E13 | G44: =F44-E44 | H44: =IF(E44=0,"",G44/ABS(E44)) | I44: =IF(AND(ABS(G44)>Dashboard!$B$6,ISNUMBER(H44),ABS(H44)>Dashboard!$C$6),"FLAG","")
A45: ='TB_2025'!A13 | B45: ='TB_2025'!B13 | C45: ='TB_2025'!C13 | D45: Mar | E45: ='TB_2025'!F13 | F45: ='TB_2026'!F13 | G45: =F45-E45 | H45: =IF(E45=0,"",G45/ABS(E45)) | I45: =IF(AND(ABS(G45)>Dashboard!$B$6,ISNUMBER(H45),ABS(H45)>Dashboard!$C$6),"FLAG","")
A46: ='TB_2025'!A13 | B46: ='TB_2025'!B13 | C46: ='TB_2025'!C13 | D46: Apr | E46: ='TB_2025'!G13 | F46: ='TB_2026'!G13 | G46: =F46-E46 | H46: =IF(E46=0,"",G46/ABS(E46)) | I46: =IF(AND(ABS(G46)>Dashboard!$B$6,ISNUMBER(H46),ABS(H46)>Dashboard!$C$6),"FLAG","")
A47: ='TB_2025'!A14 | B47: ='TB_2025'!B14 | C47: ='TB_2025'!C14 | D47: Jan | E47: ='TB_2025'!D14 | F47: ='TB_2026'!D14 | G47: =F47-E47 | H47: =IF(E47=0,"",G47/ABS(E47)) | I47: =IF(AND(ABS(G47)>Dashboard!$B$6,ISNUMBER(H47),ABS(H47)>Dashboard!$C$6),"FLAG","")
A48: ='TB_2025'!A14 | B48: ='TB_2025'!B14 | C48: ='TB_2025'!C14 | D48: Feb | E48: ='TB_2025'!E14 | F48: ='TB_2026'!E14 | G48: =F48-E48 | H48: =IF(E48=0,"",G48/ABS(E48)) | I48: =IF(AND(ABS(G48)>Dashboard!$B$6,ISNUMBER(H48),ABS(H48)>Dashboard!$C$6),"FLAG","")
A49: ='TB_2025'!A14 | B49: ='TB_2025'!B14 | C49: ='TB_2025'!C14 | D49: Mar | E49: ='TB_2025'!F14 | F49: ='TB_2026'!F14 | G49: =F49-E49 | H49: =IF(E49=0,"",G49/ABS(E49)) | I49: =IF(AND(ABS(G49)>Dashboard!$B$6,ISNUMBER(H49),ABS(H49)>Dashboard!$C$6),"FLAG","")
A50: ='TB_2025'!A14 | B50: ='TB_2025'!B14 | C50: ='TB_2025'!C14 | D50: Apr | E50: ='TB_2025'!G14 | F50: ='TB_2026'!G14 | G50: =F50-E50 | H50: =IF(E50=0,"",G50/ABS(E50)) | I50: =IF(AND(ABS(G50)>Dashboard!$B$6,ISNUMBER(H50),ABS(H50)>Dashboard!$C$6),"FLAG","")
A51: ='TB_2025'!A15 | B51: ='TB_2025'!B15 | C51: ='TB_2025'!C15 | D51: Jan | E51: ='TB_2025'!D15 | F51: ='TB_2026'!D15 | G51: =F51-E51 | H51: =IF(E51=0,"",G51/ABS(E51)) | I51: =IF(AND(ABS(G51)>Dashboard!$B$6,ISNUMBER(H51),ABS(H51)>Dashboard!$C$6),"FLAG","")
A52: ='TB_2025'!A15 | B52: ='TB_2025'!B15 | C52: ='TB_2025'!C15 | D52: Feb | E52: ='TB_2025'!E15 | F52: ='TB_2026'!E15 | G52: =F52-E52 | H52: =IF(E52=0,"",G52/ABS(E52)) | I52: =IF(AND(ABS(G52)>Dashboard!$B$6,ISNUMBER(H52),ABS(H52)>Dashboard!$C$6),"FLAG","")
A53: ='TB_2025'!A15 | B53: ='TB_2025'!B15 | C53: ='TB_2025'!C15 | D53: Mar | E53: ='TB_2025'!F15 | F53: ='TB_2026'!F15 | G53: =F53-E53 | H53: =IF(E53=0,"",G53/ABS(E53)) | I53: =IF(AND(ABS(G53)>Dashboard!$B$6,ISNUMBER(H53),ABS(H53)>Dashboard!$C$6),"FLAG","")
A54: ='TB_2025'!A15 | B54: ='TB_2025'!B15 | C54: ='TB_2025'!C15 | D54: Apr | E54: ='TB_2025'!G15 | F54: ='TB_2026'!G15 | G54: =F54-E54 | H54: =IF(E54=0,"",G54/ABS(E54)) | I54: =IF(AND(ABS(G54)>Dashboard!$B$6,ISNUMBER(H54),ABS(H54)>Dashboard!$C$6),"FLAG","")
A55: ='TB_2025'!A16 | B55: ='TB_2025'!B16 | C55: ='TB_2025'!C16 | D55: Jan | E55: ='TB_2025'!D16 | F55: ='TB_2026'!D16 | G55: =F55-E55 | H55: =IF(E55=0,"",G55/ABS(E55)) | I55: =IF(AND(ABS(G55)>Dashboard!$B$6,ISNUMBER(H55),ABS(H55)>Dashboard!$C$6),"FLAG","")
A56: ='TB_2025'!A16 | B56: ='TB_2025'!B16 | C56: ='TB_2025'!C16 | D56: Feb | E56: ='TB_2025'!E16 | F56: ='TB_2026'!E16 | G56: =F56-E56 | H56: =IF(E56=0,"",G56/ABS(E56)) | I56: =IF(AND(ABS(G56)>Dashboard!$B$6,ISNUMBER(H56),ABS(H56)>Dashboard!$C$6),"FLAG","")
A57: ='TB_2025'!A16 | B57: ='TB_2025'!B16 | C57: ='TB_2025'!C16 | D57: Mar | E57: ='TB_2025'!F16 | F57: ='TB_2026'!F16 | G57: =F57-E57 | H57: =IF(E57=0,"",G57/ABS(E57)) | I57: =IF(AND(ABS(G57)>Dashboard!$B$6,ISNUMBER(H57),ABS(H57)>Dashboard!$C$6),"FLAG","")
A58: ='TB_2025'!A16 | B58: ='TB_2025'!B16 | C58: ='TB_2025'!C16 | D58: Apr | E58: ='TB_2025'!G16 | F58: ='TB_2026'!G16 | G58: =F58-E58 | H58: =IF(E58=0,"",G58/ABS(E58)) | I58: =IF(AND(ABS(G58)>Dashboard!$B$6,ISNUMBER(H58),ABS(H58)>Dashboard!$C$6),"FLAG","")
A59: ='TB_2025'!A17 | B59: ='TB_2025'!B17 | C59: ='TB_2025'!C17 | D59: Jan | E59: ='TB_2025'!D17 | F59: ='TB_2026'!D17 | G59: =F59-E59 | H59: =IF(E59=0,"",G59/ABS(E59)) | I59: =IF(AND(ABS(G59)>Dashboard!$B$6,ISNUMBER(H59),ABS(H59)>Dashboard!$C$6),"FLAG","")
A60: ='TB_2025'!A17 | B60: ='TB_2025'!B17 | C60: ='TB_2025'!C17 | D60: Feb | E60: ='TB_2025'!E17 | F60: ='TB_2026'!E17 | G60: =F60-E60 | H60: =IF(E60=0,"",G60/ABS(E60)) | I60: =IF(AND(ABS(G60)>Dashboard!$B$6,ISNUMBER(H60),ABS(H60)>Dashboard!$C$6),"FLAG","")
A61: ='TB_2025'!A17 | B61: ='TB_2025'!B17 | C61: ='TB_2025'!C17 | D61: Mar | E61: ='TB_2025'!F17 | F61: ='TB_2026'!F17 | G61: =F61-E61 | H61: =IF(E61=0,"",G61/ABS(E61)) | I61: =IF(AND(ABS(G61)>Dashboard!$B$6,ISNUMBER(H61),ABS(H61)>Dashboard!$C$6),"FLAG","")
A62: ='TB_2025'!A17 | B62: ='TB_2025'!B17 | C62: ='TB_2025'!C17 | D62: Apr | E62: ='TB_2025'!G17 | F62: ='TB_2026'!G17 | G62: =F62-E62 | H62: =IF(E62=0,"",G62/ABS(E62)) | I62: =IF(AND(ABS(G62)>Dashboard!$B$6,ISNUMBER(H62),ABS(H62)>Dashboard!$C$6),"FLAG","")
A63: ='TB_2025'!A18 | B63: ='TB_2025'!B18 | C63: ='TB_2025'!C18 | D63: Jan | E63: ='TB_2025'!D18 | F63: ='TB_2026'!D18 | G63: =F63-E63 | H63: =IF(E63=0,"",G63/ABS(E63)) | I63: =IF(AND(ABS(G63)>Dashboard!$B$6,ISNUMBER(H63),ABS(H63)>Dashboard!$C$6),"FLAG","")
A64: ='TB_2025'!A18 | B64: ='TB_2025'!B18 | C64: ='TB_2025'!C18 | D64: Feb | E64: ='TB_2025'!E18 | F64: ='TB_2026'!E18 | G64: =F64-E64 | H64: =IF(E64=0,"",G64/ABS(E64)) | I64: =IF(AND(ABS(G64)>Dashboard!$B$6,ISNUMBER(H64),ABS(H64)>Dashboard!$C$6),"FLAG","")
A65: ='TB_2025'!A18 | B65: ='TB_2025'!B18 | C65: ='TB_2025'!C18 | D65: Mar | E65: ='TB_2025'!F18 | F65: ='TB_2026'!F18 | G65: =F65-E65 | H65: =IF(E65=0,"",G65/ABS(E65)) | I65: =IF(AND(ABS(G65)>Dashboard!$B$6,ISNUMBER(H65),ABS(H65)>Dashboard!$C$6),"FLAG","")
A66: ='TB_2025'!A18 | B66: ='TB_2025'!B18 | C66: ='TB_2025'!C18 | D66: Apr | E66: ='TB_2025'!G18 | F66: ='TB_2026'!G18 | G66: =F66-E66 | H66: =IF(E66=0,"",G66/ABS(E66)) | I66: =IF(AND(ABS(G66)>Dashboard!$B$6,ISNUMBER(H66),ABS(H66)>Dashboard!$C$6),"FLAG","")
A67: ='TB_2025'!A19 | B67: ='TB_2025'!B19 | C67: ='TB_2025'!C19 | D67: Jan | E67: ='TB_2025'!D19 | F67: ='TB_2026'!D19 | G67: =F67-E67 | H67: =IF(E67=0,"",G67/ABS(E67)) | I67: =IF(AND(ABS(G67)>Dashboard!$B$6,ISNUMBER(H67),ABS(H67)>Dashboard!$C$6),"FLAG","")
A68: ='TB_2025'!A19 | B68: ='TB_2025'!B19 | C68: ='TB_2025'!C19 | D68: Feb | E68: ='TB_2025'!E19 | F68: ='TB_2026'!E19 | G68: =F68-E68 | H68: =IF(E68=0,"",G68/ABS(E68)) | I68: =IF(AND(ABS(G68)>Dashboard!$B$6,ISNUMBER(H68),ABS(H68)>Dashboard!$C$6),"FLAG","")
A69: ='TB_2025'!A19 | B69: ='TB_2025'!B19 | C69: ='TB_2025'!C19 | D69: Mar | E69: ='TB_2025'!F19 | F69: ='TB_2026'!F19 | G69: =F69-E69 | H69: =IF(E69=0,"",G69/ABS(E69)) | I69: =IF(AND(ABS(G69)>Dashboard!$B$6,ISNUMBER(H69),ABS(H69)>Dashboard!$C$6),"FLAG","")
A70: ='TB_2025'!A19 | B70: ='TB_2025'!B19 | C70: ='TB_2025'!C19 | D70: Apr | E70: ='TB_2025'!G19 | F70: ='TB_2026'!G19 | G70: =F70-E70 | H70: =IF(E70=0,"",G70/ABS(E70)) | I70: =IF(AND(ABS(G70)>Dashboard!$B$6,ISNUMBER(H70),ABS(H70)>Dashboard!$C$6),"FLAG","")
A71: ='TB_2025'!A20 | B71: ='TB_2025'!B20 | C71: ='TB_2025'!C20 | D71: Jan | E71: ='TB_2025'!D20 | F71: ='TB_2026'!D20 | G71: =F71-E71 | H71: =IF(E71=0,"",G71/ABS(E71)) | I71: =IF(AND(ABS(G71)>Dashboard!$B$6,ISNUMBER(H71),ABS(H71)>Dashboard!$C$6),"FLAG","")
A72: ='TB_2025'!A20 | B72: ='TB_2025'!B20 | C72: ='TB_2025'!C20 | D72: Feb | E72: ='TB_2025'!E20 | F72: ='TB_2026'!E20 | G72: =F72-E72 | H72: =IF(E72=0,"",G72/ABS(E72)) | I72: =IF(AND(ABS(G72)>Dashboard!$B$6,ISNUMBER(H72),ABS(H72)>Dashboard!$C$6),"FLAG","")
A73: ='TB_2025'!A20 | B73: ='TB_2025'!B20 | C73: ='TB_2025'!C20 | D73: Mar | E73: ='TB_2025'!F20 | F73: ='TB_2026'!F20 | G73: =F73-E73 | H73: =IF(E73=0,"",G73/ABS(E73)) | I73: =IF(AND(ABS(G73)>Dashboard!$B$6,ISNUMBER(H73),ABS(H73)>Dashboard!$C$6),"FLAG","")
A74: ='TB_2025'!A20 | B74: ='TB_2025'!B20 | C74: ='TB_2025'!C20 | D74: Apr | E74: ='TB_2025'!G20 | F74: ='TB_2026'!G20 | G74: =F74-E74 | H74: =IF(E74=0,"",G74/ABS(E74)) | I74: =IF(AND(ABS(G74)>Dashboard!$B$6,ISNUMBER(H74),ABS(H74)>Dashboard!$C$6),"FLAG","")
A75: ='TB_2025'!A21 | B75: ='TB_2025'!B21 | C75: ='TB_2025'!C21 | D75: Jan | E75: ='TB_2025'!D21 | F75: ='TB_2026'!D21 | G75: =F75-E75 | H75: =IF(E75=0,"",G75/ABS(E75)) | I75: =IF(AND(ABS(G75)>Dashboard!$B$6,ISNUMBER(H75),ABS(H75)>Dashboard!$C$6),"FLAG","")
A76: ='TB_2025'!A21 | B76: ='TB_2025'!B21 | C76: ='TB_2025'!C21 | D76: Feb | E76: ='TB_2025'!E21 | F76: ='TB_2026'!E21 | G76: =F76-E76 | H76: =IF(E76=0,"",G76/ABS(E76)) | I76: =IF(AND(ABS(G76)>Dashboard!$B$6,ISNUMBER(H76),ABS(H76)>Dashboard!$C$6),"FLAG","")
A77: ='TB_2025'!A21 | B77: ='TB_2025'!B21 | C77: ='TB_2025'!C21 | D77: Mar | E77: ='TB_2025'!F21 | F77: ='TB_2026'!F21 | G77: =F77-E77 | H77: =IF(E77=0,"",G77/ABS(E77)) | I77: =IF(AND(ABS(G77)>Dashboard!$B$6,ISNUMBER(H77),ABS(H77)>Dashboard!$C$6),"FLAG","")
A78: ='TB_2025'!A21 | B78: ='TB_2025'!B21 | C78: ='TB_2025'!C21 | D78: Apr | E78: ='TB_2025'!G21 | F78: ='TB_2026'!G21 | G78: =F78-E78 | H78: =IF(E78=0,"",G78/ABS(E78)) | I78: =IF(AND(ABS(G78)>Dashboard!$B$6,ISNUMBER(H78),ABS(H78)>Dashboard!$C$6),"FLAG","")
A79: ='TB_2025'!A22 | B79: ='TB_2025'!B22 | C79: ='TB_2025'!C22 | D79: Jan | E79: ='TB_2025'!D22 | F79: ='TB_2026'!D22 | G79: =F79-E79 | H79: =IF(E79=0,"",G79/ABS(E79)) | I79: =IF(AND(ABS(G79)>Dashboard!$B$6,ISNUMBER(H79),ABS(H79)>Dashboard!$C$6),"FLAG","")
A80: ='TB_2025'!A22 | B80: ='TB_2025'!B22 | C80: ='TB_2025'!C22 | D80: Feb | E80: ='TB_2025'!E22 | F80: ='TB_2026'!E22 | G80: =F80-E80 | H80: =IF(E80=0,"",G80/ABS(E80)) | I80: =IF(AND(ABS(G80)>Dashboard!$B$6,ISNUMBER(H80),ABS(H80)>Dashboard!$C$6),"FLAG","")
A81: ='TB_2025'!A22 | B81: ='TB_2025'!B22 | C81: ='TB_2025'!C22 | D81: Mar | E81: ='TB_2025'!F22 | F81: ='TB_2026'!F22 | G81: =F81-E81 | H81: =IF(E81=0,"",G81/ABS(E81)) | I81: =IF(AND(ABS(G81)>Dashboard!$B$6,ISNUMBER(H81),ABS(H81)>Dashboard!$C$6),"FLAG","")
A82: ='TB_2025'!A22 | B82: ='TB_2025'!B22 | C82: ='TB_2025'!C22 | D82: Apr | E82: ='TB_2025'!G22 | F82: ='TB_2026'!G22 | G82: =F82-E82 | H82: =IF(E82=0,"",G82/ABS(E82)) | I82: =IF(AND(ABS(G82)>Dashboard!$B$6,ISNUMBER(H82),ABS(H82)>Dashboard!$C$6),"FLAG","")
A83: ='TB_2025'!A23 | B83: ='TB_2025'!B23 | C83: ='TB_2025'!C23 | D83: Jan | E83: ='TB_2025'!D23 | F83: ='TB_2026'!D23 | G83: =F83-E83 | H83: =IF(E83=0,"",G83/ABS(E83)) | I83: =IF(AND(ABS(G83)>Dashboard!$B$6,ISNUMBER(H83),ABS(H83)>Dashboard!$C$6),"FLAG","")
A84: ='TB_2025'!A23 | B84: ='TB_2025'!B23 | C84: ='TB_2025'!C23 | D84: Feb | E84: ='TB_2025'!E23 | F84: ='TB_2026'!E23 | G84: =F84-E84 | H84: =IF(E84=0,"",G84/ABS(E84)) | I84: =IF(AND(ABS(G84)>Dashboard!$B$6,ISNUMBER(H84),ABS(H84)>Dashboard!$C$6),"FLAG","")
A85: ='TB_2025'!A23 | B85: ='TB_2025'!B23 | C85: ='TB_2025'!C23 | D85: Mar | E85: ='TB_2025'!F23 | F85: ='TB_2026'!F23 | G85: =F85-E85 | H85: =IF(E85=0,"",G85/ABS(E85)) | I85: =IF(AND(ABS(G85)>Dashboard!$B$6,ISNUMBER(H85),ABS(H85)>Dashboard!$C$6),"FLAG","")
A86: ='TB_2025'!A23 | B86: ='TB_2025'!B23 | C86: ='TB_2025'!C23 | D86: Apr | E86: ='TB_2025'!G23 | F86: ='TB_2026'!G23 | G86: =F86-E86 | H86: =IF(E86=0,"",G86/ABS(E86)) | I86: =IF(AND(ABS(G86)>Dashboard!$B$6,ISNUMBER(H86),ABS(H86)>Dashboard!$C$6),"FLAG","")
A87: ='TB_2025'!A24 | B87: ='TB_2025'!B24 | C87: ='TB_2025'!C24 | D87: Jan | E87: ='TB_2025'!D24 | F87: ='TB_2026'!D24 | G87: =F87-E87 | H87: =IF(E87=0,"",G87/ABS(E87)) | I87: =IF(AND(ABS(G87)>Dashboard!$B$6,ISNUMBER(H87),ABS(H87)>Dashboard!$C$6),"FLAG","")
A88: ='TB_2025'!A24 | B88: ='TB_2025'!B24 | C88: ='TB_2025'!C24 | D88: Feb | E88: ='TB_2025'!E24 | F88: ='TB_2026'!E24 | G88: =F88-E88 | H88: =IF(E88=0,"",G88/ABS(E88)) | I88: =IF(AND(ABS(G88)>Dashboard!$B$6,ISNUMBER(H88),ABS(H88)>Dashboard!$C$6),"FLAG","")
A89: ='TB_2025'!A24 | B89: ='TB_2025'!B24 | C89: ='TB_2025'!C24 | D89: Mar | E89: ='TB_2025'!F24 | F89: ='TB_2026'!F24 | G89: =F89-E89 | H89: =IF(E89=0,"",G89/ABS(E89)) | I89: =IF(AND(ABS(G89)>Dashboard!$B$6,ISNUMBER(H89),ABS(H89)>Dashboard!$C$6),"FLAG","")
A90: ='TB_2025'!A24 | B90: ='TB_2025'!B24 | C90: ='TB_2025'!C24 | D90: Apr | E90: ='TB_2025'!G24 | F90: ='TB_2026'!G24 | G90: =F90-E90 | H90: =IF(E90=0,"",G90/ABS(E90)) | I90: =IF(AND(ABS(G90)>Dashboard!$B$6,ISNUMBER(H90),ABS(H90)>Dashboard!$C$6),"FLAG","")
A91: ='TB_2025'!A25 | B91: ='TB_2025'!B25 | C91: ='TB_2025'!C25 | D91: Jan | E91: ='TB_2025'!D25 | F91: ='TB_2026'!D25 | G91: =F91-E91 | H91: =IF(E91=0,"",G91/ABS(E91)) | I91: =IF(AND(ABS(G91)>Dashboard!$B$6,ISNUMBER(H91),ABS(H91)>Dashboard!$C$6),"FLAG","")
A92: ='TB_2025'!A25 | B92: ='TB_2025'!B25 | C92: ='TB_2025'!C25 | D92: Feb | E92: ='TB_2025'!E25 | F92: ='TB_2026'!E25 | G92: =F92-E92 | H92: =IF(E92=0,"",G92/ABS(E92)) | I92: =IF(AND(ABS(G92)>Dashboard!$B$6,ISNUMBER(H92),ABS(H92)>Dashboard!$C$6),"FLAG","")
A93: ='TB_2025'!A25 | B93: ='TB_2025'!B25 | C93: ='TB_2025'!C25 | D93: Mar | E93: ='TB_2025'!F25 | F93: ='TB_2026'!F25 | G93: =F93-E93 | H93: =IF(E93=0,"",G93/ABS(E93)) | I93: =IF(AND(ABS(G93)>Dashboard!$B$6,ISNUMBER(H93),ABS(H93)>Dashboard!$C$6),"FLAG","")
A94: ='TB_2025'!A25 | B94: ='TB_2025'!B25 | C94: ='TB_2025'!C25 | D94: Apr | E94: ='TB_2025'!G25 | F94: ='TB_2026'!G25 | G94: =F94-E94 | H94: =IF(E94=0,"",G94/ABS(E94)) | I94: =IF(AND(ABS(G94)>Dashboard!$B$6,ISNUMBER(H94),ABS(H94)>Dashboard!$C$6),"FLAG","")
A95: ='TB_2025'!A26 | B95: ='TB_2025'!B26 | C95: ='TB_2025'!C26 | D95: Jan | E95: ='TB_2025'!D26 | F95: ='TB_2026'!D26 | G95: =F95-E95 | H95: =IF(E95=0,"",G95/ABS(E95)) | I95: =IF(AND(ABS(G95)>Dashboard!$B$6,ISNUMBER(H95),ABS(H95)>Dashboard!$C$6),"FLAG","")
A96: ='TB_2025'!A26 | B96: ='TB_2025'!B26 | C96: ='TB_2025'!C26 | D96: Feb | E96: ='TB_2025'!E26 | F96: ='TB_2026'!E26 | G96: =F96-E96 | H96: =IF(E96=0,"",G96/ABS(E96)) | I96: =IF(AND(ABS(G96)>Dashboard!$B$6,ISNUMBER(H96),ABS(H96)>Dashboard!$C$6),"FLAG","")
A97: ='TB_2025'!A26 | B97: ='TB_2025'!B26 | C97: ='TB_2025'!C26 | D97: Mar | E97: ='TB_2025'!F26 | F97: ='TB_2026'!F26 | G97: =F97-E97 | H97: =IF(E97=0,"",G97/ABS(E97)) | I97: =IF(AND(ABS(G97)>Dashboard!$B$6,ISNUMBER(H97),ABS(H97)>Dashboard!$C$6),"FLAG","")
A98: ='TB_2025'!A26 | B98: ='TB_2025'!B26 | C98: ='TB_2025'!C26 | D98: Apr | E98: ='TB_2025'!G26 | F98: ='TB_2026'!G26 | G98: =F98-E98 | H98: =IF(E98=0,"",G98/ABS(E98)) | I98: =IF(AND(ABS(G98)>Dashboard!$B$6,ISNUMBER(H98),ABS(H98)>Dashboard!$C$6),"FLAG","")
A99: ='TB_2025'!A27 | B99: ='TB_2025'!B27 | C99: ='TB_2025'!C27 | D99: Jan | E99: ='TB_2025'!D27 | F99: ='TB_2026'!D27 | G99: =F99-E99 | H99: =IF(E99=0,"",G99/ABS(E99)) | I99: =IF(AND(ABS(G99)>Dashboard!$B$6,ISNUMBER(H99),ABS(H99)>Dashboard!$C$6),"FLAG","")
A100: ='TB_2025'!A27 | B100: ='TB_2025'!B27 | C100: ='TB_2025'!C27 | D100: Feb | E100: ='TB_2025'!E27 | F100: ='TB_2026'!E27 | G100: =F100-E100 | H100: =IF(E100=0,"",G100/ABS(E100)) | I100: =IF(AND(ABS(G100)>Dashboard!$B$6,ISNUMBER(H100),ABS(H100)>Dashboard!$C$6),"FLAG","")
...

Sheet MoM_Variance
A1: Month-over-Month Variance - sequential months, 2026 only
A2: Account Code | B2: Account | C2: Type | D2: From | E2: To | F2: Value (From) | G2: Value (To) | H2: $ Var | I2: % Var | J2: Flag
A3: ='TB_2026'!A3 | B3: ='TB_2026'!B3 | C3: ='TB_2026'!C3 | D3: Jan | E3: Feb | F3: ='TB_2026'!D3 | G3: ='TB_2026'!E3 | H3: =G3-F3 | I3: =IF(F3=0,"",H3/ABS(F3)) | J3: =IF(AND(ABS(H3)>Dashboard!$B$7,ISNUMBER(I3),ABS(I3)>Dashboard!$C$7),"FLAG","")
A4: ='TB_2026'!A3 | B4: ='TB_2026'!B3 | C4: ='TB_2026'!C3 | D4: Feb | E4: Mar | F4: ='TB_2026'!E3 | G4: ='TB_2026'!F3 | H4: =G4-F4 | I4: =IF(F4=0,"",H4/ABS(F4)) | J4: =IF(AND(ABS(H4)>Dashboard!$B$7,ISNUMBER(I4),ABS(I4)>Dashboard!$C$7),"FLAG","")
A5: ='TB_2026'!A3 | B5: ='TB_2026'!B3 | C5: ='TB_2026'!C3 | D5: Mar | E5: Apr | F5: ='TB_2026'!F3 | G5: ='TB_2026'!G3 | H5: =G5-F5 | I5: =IF(F5=0,"",H5/ABS(F5)) | J5: =IF(AND(ABS(H5)>Dashboard!$B$7,ISNUMBER(I5),ABS(I5)>Dashboard!$C$7),"FLAG","")
A6: ='TB_2026'!A4 | B6: ='TB_2026'!B4 | C6: ='TB_2026'!C4 | D6: Jan | E6: Feb | F6: ='TB_2026'!D4 | G6: ='TB_2026'!E4 | H6: =G6-F6 | I6: =IF(F6=0,"",H6/ABS(F6)) | J6: =IF(AND(ABS(H6)>Dashboard!$B$7,ISNUMBER(I6),ABS(I6)>Dashboard!$C$7),"FLAG","")
A7: ='TB_2026'!A4 | B7: ='TB_2026'!B4 | C7: ='TB_2026'!C4 | D7: Feb | E7: Mar | F7: ='TB_2026'!E4 | G7: ='TB_2026'!F4 | H7: =G7-F7 | I7: =IF(F7=0,"",H7/ABS(F7)) | J7: =IF(AND(ABS(H7)>Dashboard!$B$7,ISNUMBER(I7),ABS(I7)>Dashboard!$C$7),"FLAG","")
A8: ='TB_2026'!A4 | B8: ='TB_2026'!B4 | C8: ='TB_2026'!C4 | D8: Mar | E8: Apr | F8: ='TB_2026'!F4 | G8: ='TB_2026'!G4 | H8: =G8-F8 | I8: =IF(F8=0,"",H8/ABS(F8)) | J8: =IF(AND(ABS(H8)>Dashboard!$B$7,ISNUMBER(I8),ABS(I8)>Dashboard!$C$7),"FLAG","")
A9: ='TB_2026'!A5 | B9: ='TB_2026'!B5 | C9: ='TB_2026'!C5 | D9: Jan | E9: Feb | F9: ='TB_2026'!D5 | G9: ='TB_2026'!E5 | H9: =G9-F9 | I9: =IF(F9=0,"",H9/ABS(F9)) | J9: =IF(AND(ABS(H9)>Dashboard!$B$7,ISNUMBER(I9),ABS(I9)>Dashboard!$C$7),"FLAG","")
A10: ='TB_2026'!A5 | B10: ='TB_2026'!B5 | C10: ='TB_2026'!C5 | D10: Feb | E10: Mar | F10: ='TB_2026'!E5 | G10: ='TB_2026'!F5 | H10: =G10-F10 | I10: =IF(F10=0,"",H10/ABS(F10)) | J10: =IF(AND(ABS(H10)>Dashboard!$B$7,ISNUMBER(I10),ABS(I10)>Dashboard!$C$7),"FLAG","")
A11: ='TB_2026'!A5 | B11: ='TB_2026'!B5 | C11: ='TB_2026'!C5 | D11: Mar | E11: Apr | F11: ='TB_2026'!F5 | G11: ='TB_2026'!G5 | H11: =G11-F11 | I11: =IF(F11=0,"",H11/ABS(F11)) | J11: =IF(AND(ABS(H11)>Dashboard!$B$7,ISNUMBER(I11),ABS(I11)>Dashboard!$C$7),"FLAG","")
A12: ='TB_2026'!A6 | B12: ='TB_2026'!B6 | C12: ='TB_2026'!C6 | D12: Jan | E12: Feb | F12: ='TB_2026'!D6 | G12: ='TB_2026'!E6 | H12: =G12-F12 | I12: =IF(F12=0,"",H12/ABS(F12)) | J12: =IF(AND(ABS(H12)>Dashboard!$B$7,ISNUMBER(I12),ABS(I12)>Dashboard!$C$7),"FLAG","")
A13: ='TB_2026'!A6 | B13: ='TB_2026'!B6 | C13: ='TB_2026'!C6 | D13: Feb | E13: Mar | F13: ='TB_2026'!E6 | G13: ='TB_2026'!F6 | H13: =G13-F13 | I13: =IF(F13=0,"",H13/ABS(F13)) | J13: =IF(AND(ABS(H13)>Dashboard!$B$7,ISNUMBER(I13),ABS(I13)>Dashboard!$C$7),"FLAG","")
A14: ='TB_2026'!A6 | B14: ='TB_2026'!B6 | C14: ='TB_2026'!C6 | D14: Mar | E14: Apr | F14: ='TB_2026'!F6 | G14: ='TB_2026'!G6 | H14: =G14-F14 | I14: =IF(F14=0,"",H14/ABS(F14)) | J14: =IF(AND(ABS(H14)>Dashboard!$B$7,ISNUMBER(I14),ABS(I14)>Dashboard!$C$7),"FLAG","")
A15: ='TB_2026'!A7 | B15: ='TB_2026'!B7 | C15: ='TB_2026'!C7 | D15: Jan | E15: Feb | F15: ='TB_2026'!D7 | G15: ='TB_2026'!E7 | H15: =G15-F15 | I15: =IF(F15=0,"",H15/ABS(F15)) | J15: =IF(AND(ABS(H15)>Dashboard!$B$7,ISNUMBER(I15),ABS(I15)>Dashboard!$C$7),"FLAG","")
A16: ='TB_2026'!A7 | B16: ='TB_2026'!B7 | C16: ='TB_2026'!C7 | D16: Feb | E16: Mar | F16: ='TB_2026'!E7 | G16: ='TB_2026'!F7 | H16: =G16-F16 | I16: =IF(F16=0,"",H16/ABS(F16)) | J16: =IF(AND(ABS(H16)>Dashboard!$B$7,ISNUMBER(I16),ABS(I16)>Dashboard!$C$7),"FLAG","")
A17: ='TB_2026'!A7 | B17: ='TB_2026'!B7 | C17: ='TB_2026'!C7 | D17: Mar | E17: Apr | F17: ='TB_2026'!F7 | G17: ='TB_2026'!G7 | H17: =G17-F17 | I17: =IF(F17=0,"",H17/ABS(F17)) | J17: =IF(AND(ABS(H17)>Dashboard!$B$7,ISNUMBER(I17),ABS(I17)>Dashboard!$C$7),"FLAG","")
A18: ='TB_2026'!A8 | B18: ='TB_2026'!B8 | C18: ='TB_2026'!C8 | D18: Jan | E18: Feb | F18: ='TB_2026'!D8 | G18: ='TB_2026'!E8 | H18: =G18-F18 | I18: =IF(F18=0,"",H18/ABS(F18)) | J18: =IF(AND(ABS(H18)>Dashboard!$B$7,ISNUMBER(I18),ABS(I18)>Dashboard!$C$7),"FLAG","")
A19: ='TB_2026'!A8 | B19: ='TB_2026'!B8 | C19: ='TB_2026'!C8 | D19: Feb | E19: Mar | F19: ='TB_2026'!E8 | G19: ='TB_2026'!F8 | H19: =G19-F19 | I19: =IF(F19=0,"",H19/ABS(F19)) | J19: =IF(AND(ABS(H19)>Dashboard!$B$7,ISNUMBER(I19),ABS(I19)>Dashboard!$C$7),"FLAG","")
A20: ='TB_2026'!A8 | B20: ='TB_2026'!B8 | C20: ='TB_2026'!C8 | D20: Mar | E20: Apr | F20: ='TB_2026'!F8 | G20: ='TB_2026'!G8 | H20: =G20-F20 | I20: =IF(F20=0,"",H20/ABS(F20)) | J20: =IF(AND(ABS(H20)>Dashboard!$B$7,ISNUMBER(I20),ABS(I20)>Dashboard!$C$7),"FLAG","")
A21: ='TB_2026'!A9 | B21: ='TB_2026'!B9 | C21: ='TB_2026'!C9 | D21: Jan | E21: Feb | F21: ='TB_2026'!D9 | G21: ='TB_2026'!E9 | H21: =G21-F21 | I21: =IF(F21=0,"",H21/ABS(F21)) | J21: =IF(AND(ABS(H21)>Dashboard!$B$7,ISNUMBER(I21),ABS(I21)>Dashboard!$C$7),"FLAG","")
A22: ='TB_2026'!A9 | B22: ='TB_2026'!B9 | C22: ='TB_2026'!C9 | D22: Feb | E22: Mar | F22: ='TB_2026'!E9 | G22: ='TB_2026'!F9 | H22: =G22-F22 | I22: =IF(F22=0,"",H22/ABS(F22)) | J22: =IF(AND(ABS(H22)>Dashboard!$B$7,ISNUMBER(I22),ABS(I22)>Dashboard!$C$7),"FLAG","")
A23: ='TB_2026'!A9 | B23: ='TB_2026'!B9 | C23: ='TB_2026'!C9 | D23: Mar | E23: Apr | F23: ='TB_2026'!F9 | G23: ='TB_2026'!G9 | H23: =G23-F23 | I23: =IF(F23=0,"",H23/ABS(F23)) | J23: =IF(AND(ABS(H23)>Dashboard!$B$7,ISNUMBER(I23),ABS(I23)>Dashboard!$C$7),"FLAG","")
A24: ='TB_2026'!A10 | B24: ='TB_2026'!B10 | C24: ='TB_2026'!C10 | D24: Jan | E24: Feb | F24: ='TB_2026'!D10 | G24: ='TB_2026'!E10 | H24: =G24-F24 | I24: =IF(F24=0,"",H24/ABS(F24)) | J24: =IF(AND(ABS(H24)>Dashboard!$B$7,ISNUMBER(I24),ABS(I24)>Dashboard!$C$7),"FLAG","")
A25: ='TB_2026'!A10 | B25: ='TB_2026'!B10 | C25: ='TB_2026'!C10 | D25: Feb | E25: Mar | F25: ='TB_2026'!E10 | G25: ='TB_2026'!F10 | H25: =G25-F25 | I25: =IF(F25=0,"",H25/ABS(F25)) | J25: =IF(AND(ABS(H25)>Dashboard!$B$7,ISNUMBER(I25),ABS(I25)>Dashboard!$C$7),"FLAG","")
A26: ='TB_2026'!A10 | B26: ='TB_2026'!B10 | C26: ='TB_2026'!C10 | D26: Mar | E26: Apr | F26: ='TB_2026'!F10 | G26: ='TB_2026'!G10 | H26: =G26-F26 | I26: =IF(F26=0,"",H26/ABS(F26)) | J26: =IF(AND(ABS(H26)>Dashboard!$B$7,ISNUMBER(I26),ABS(I26)>Dashboard!$C$7),"FLAG","")
A27: ='TB_2026'!A11 | B27: ='TB_2026'!B11 | C27: ='TB_2026'!C11 | D27: Jan | E27: Feb | F27: ='TB_2026'!D11 | G27: ='TB_2026'!E11 | H27: =G27-F27 | I27: =IF(F27=0,"",H27/ABS(F27)) | J27: =IF(AND(ABS(H27)>Dashboard!$B$7,ISNUMBER(I27),ABS(I27)>Dashboard!$C$7),"FLAG","")
A28: ='TB_2026'!A11 | B28: ='TB_2026'!B11 | C28: ='TB_2026'!C11 | D28: Feb | E28: Mar | F28: ='TB_2026'!E11 | G28: ='TB_2026'!F11 | H28: =G28-F28 | I28: =IF(F28=0,"",H28/ABS(F28)) | J28: =IF(AND(ABS(H28)>Dashboard!$B$7,ISNUMBER(I28),ABS(I28)>Dashboard!$C$7),"FLAG","")
A29: ='TB_2026'!A11 | B29: ='TB_2026'!B11 | C29: ='TB_2026'!C11 | D29: Mar | E29: Apr | F29: ='TB_2026'!F11 | G29: ='TB_2026'!G11 | H29: =G29-F29 | I29: =IF(F29=0,"",H29/ABS(F29)) | J29: =IF(AND(ABS(H29)>Dashboard!$B$7,ISNUMBER(I29),ABS(I29)>Dashboard!$C$7),"FLAG","")
A30: ='TB_2026'!A12 | B30: ='TB_2026'!B12 | C30: ='TB_2026'!C12 | D30: Jan | E30: Feb | F30: ='TB_2026'!D12 | G30: ='TB_2026'!E12 | H30: =G30-F30 | I30: =IF(F30=0,"",H30/ABS(F30)) | J30: =IF(AND(ABS(H30)>Dashboard!$B$7,ISNUMBER(I30),ABS(I30)>Dashboard!$C$7),"FLAG","")
A31: ='TB_2026'!A12 | B31: ='TB_2026'!B12 | C31: ='TB_2026'!C12 | D31: Feb | E31: Mar | F31: ='TB_2026'!E12 | G31: ='TB_2026'!F12 | H31: =G31-F31 | I31: =IF(F31=0,"",H31/ABS(F31)) | J31: =IF(AND(ABS(H31)>Dashboard!$B$7,ISNUMBER(I31),ABS(I31)>Dashboard!$C$7),"FLAG","")
A32: ='TB_2026'!A12 | B32: ='TB_2026'!B12 | C32: ='TB_2026'!C12 | D32: Mar | E32: Apr | F32: ='TB_2026'!F12 | G32: ='TB_2026'!G12 | H32: =G32-F32 | I32: =IF(F32=0,"",H32/ABS(F32)) | J32: =IF(AND(ABS(H32)>Dashboard!$B$7,ISNUMBER(I32),ABS(I32)>Dashboard!$C$7),"FLAG","")
A33: ='TB_2026'!A13 | B33: ='TB_2026'!B13 | C33: ='TB_2026'!C13 | D33: Jan | E33: Feb | F33: ='TB_2026'!D13 | G33: ='TB_2026'!E13 | H33: =G33-F33 | I33: =IF(F33=0,"",H33/ABS(F33)) | J33: =IF(AND(ABS(H33)>Dashboard!$B$7,ISNUMBER(I33),ABS(I33)>Dashboard!$C$7),"FLAG","")
A34: ='TB_2026'!A13 | B34: ='TB_2026'!B13 | C34: ='TB_2026'!C13 | D34: Feb | E34: Mar | F34: ='TB_2026'!E13 | G34: ='TB_2026'!F13 | H34: =G34-F34 | I34: =IF(F34=0,"",H34/ABS(F34)) | J34: =IF(AND(ABS(H34)>Dashboard!$B$7,ISNUMBER(I34),ABS(I34)>Dashboard!$C$7),"FLAG","")
A35: ='TB_2026'!A13 | B35: ='TB_2026'!B13 | C35: ='TB_2026'!C13 | D35: Mar | E35: Apr | F35: ='TB_2026'!F13 | G35: ='TB_2026'!G13 | H35: =G35-F35 | I35: =IF(F35=0,"",H35/ABS(F35)) | J35: =IF(AND(ABS(H35)>Dashboard!$B$7,ISNUMBER(I35),ABS(I35)>Dashboard!$C$7),"FLAG","")
A36: ='TB_2026'!A14 | B36: ='TB_2026'!B14 | C36: ='TB_2026'!C14 | D36: Jan | E36: Feb | F36: ='TB_2026'!D14 | G36: ='TB_2026'!E14 | H36: =G36-F36 | I36: =IF(F36=0,"",H36/ABS(F36)) | J36: =IF(AND(ABS(H36)>Dashboard!$B$7,ISNUMBER(I36),ABS(I36)>Dashboard!$C$7),"FLAG","")
A37: ='TB_2026'!A14 | B37: ='TB_2026'!B14 | C37: ='TB_2026'!C14 | D37: Feb | E37: Mar | F37: ='TB_2026'!E14 | G37: ='TB_2026'!F14 | H37: =G37-F37 | I37: =IF(F37=0,"",H37/ABS(F37)) | J37: =IF(AND(ABS(H37)>Dashboard!$B$7,ISNUMBER(I37),ABS(I37)>Dashboard!$C$7),"FLAG","")
A38: ='TB_2026'!A14 | B38: ='TB_2026'!B14 | C38: ='TB_2026'!C14 | D38: Mar | E38: Apr | F38: ='TB_2026'!F14 | G38: ='TB_2026'!G14 | H38: =G38-F38 | I38: =IF(F38=0,"",H38/ABS(F38)) | J38: =IF(AND(ABS(H38)>Dashboard!$B$7,ISNUMBER(I38),ABS(I38)>Dashboard!$C$7),"FLAG","")
A39: ='TB_2026'!A15 | B39: ='TB_2026'!B15 | C39: ='TB_2026'!C15 | D39: Jan | E39: Feb | F39: ='TB_2026'!D15 | G39: ='TB_2026'!E15 | H39: =G39-F39 | I39: =IF(F39=0,"",H39/ABS(F39)) | J39: =IF(AND(ABS(H39)>Dashboard!$B$7,ISNUMBER(I39),ABS(I39)>Dashboard!$C$7),"FLAG","")
A40: ='TB_2026'!A15 | B40: ='TB_2026'!B15 | C40: ='TB_2026'!C15 | D40: Feb | E40: Mar | F40: ='TB_2026'!E15 | G40: ='TB_2026'!F15 | H40: =G40-F40 | I40: =IF(F40=0,"",H40/ABS(F40)) | J40: =IF(AND(ABS(H40)>Dashboard!$B$7,ISNUMBER(I40),ABS(I40)>Dashboard!$C$7),"FLAG","")
A41: ='TB_2026'!A15 | B41: ='TB_2026'!B15 | C41: ='TB_2026'!C15 | D41: Mar | E41: Apr | F41: ='TB_2026'!F15 | G41: ='TB_2026'!G15 | H41: =G41-F41 | I41: =IF(F41=0,"",H41/ABS(F41)) | J41: =IF(AND(ABS(H41)>Dashboard!$B$7,ISNUMBER(I41),ABS(I41)>Dashboard!$C$7),"FLAG","")
A42: ='TB_2026'!A16 | B42: ='TB_2026'!B16 | C42: ='TB_2026'!C16 | D42: Jan | E42: Feb | F42: ='TB_2026'!D16 | G42: ='TB_2026'!E16 | H42: =G42-F42 | I42: =IF(F42=0,"",H42/ABS(F42)) | J42: =IF(AND(ABS(H42)>Dashboard!$B$7,ISNUMBER(I42),ABS(I42)>Dashboard!$C$7),"FLAG","")
A43: ='TB_2026'!A16 | B43: ='TB_2026'!B16 | C43: ='TB_2026'!C16 | D43: Feb | E43: Mar | F43: ='TB_2026'!E16 | G43: ='TB_2026'!F16 | H43: =G43-F43 | I43: =IF(F43=0,"",H43/ABS(F43)) | J43: =IF(AND(ABS(H43)>Dashboard!$B$7,ISNUMBER(I43),ABS(I43)>Dashboard!$C$7),"FLAG","")
A44: ='TB_2026'!A16 | B44: ='TB_2026'!B16 | C44: ='TB_2026'!C16 | D44: Mar | E44: Apr | F44: ='TB_2026'!F16 | G44: ='TB_2026'!G16 | H44: =G44-F44 | I44: =IF(F44=0,"",H44/ABS(F44)) | J44: =IF(AND(ABS(H44)>Dashboard!$B$7,ISNUMBER(I44),ABS(I44)>Dashboard!$C$7),"FLAG","")
A45: ='TB_2026'!A17 | B45: ='TB_2026'!B17 | C45: ='TB_2026'!C17 | D45: Jan | E45: Feb | F45: ='TB_2026'!D17 | G45: ='TB_2026'!E17 | H45: =G45-F45 | I45: =IF(F45=0,"",H45/ABS(F45)) | J45: =IF(AND(ABS(H45)>Dashboard!$B$7,ISNUMBER(I45),ABS(I45)>Dashboard!$C$7),"FLAG","")
A46: ='TB_2026'!A17 | B46: ='TB_2026'!B17 | C46: ='TB_2026'!C17 | D46: Feb | E46: Mar | F46: ='TB_2026'!E17 | G46: ='TB_2026'!F17 | H46: =G46-F46 | I46: =IF(F46=0,"",H46/ABS(F46)) | J46: =IF(AND(ABS(H46)>Dashboard!$B$7,ISNUMBER(I46),ABS(I46)>Dashboard!$C$7),"FLAG","")
A47: ='TB_2026'!A17 | B47: ='TB_2026'!B17 | C47: ='TB_2026'!C17 | D47: Mar | E47: Apr | F47: ='TB_2026'!F17 | G47: ='TB_2026'!G17 | H47: =G47-F47 | I47: =IF(F47=0,"",H47/ABS(F47)) | J47: =IF(AND(ABS(H47)>Dashboard!$B$7,ISNUMBER(I47),ABS(I47)>Dashboard!$C$7),"FLAG","")
A48: ='TB_2026'!A18 | B48: ='TB_2026'!B18 | C48: ='TB_2026'!C18 | D48: Jan | E48: Feb | F48: ='TB_2026'!D18 | G48: ='TB_2026'!E18 | H48: =G48-F48 | I48: =IF(F48=0,"",H48/ABS(F48)) | J48: =IF(AND(ABS(H48)>Dashboard!$B$7,ISNUMBER(I48),ABS(I48)>Dashboard!$C$7),"FLAG","")
A49: ='TB_2026'!A18 | B49: ='TB_2026'!B18 | C49: ='TB_2026'!C18 | D49: Feb | E49: Mar | F49: ='TB_2026'!E18 | G49: ='TB_2026'!F18 | H49: =G49-F49 | I49: =IF(F49=0,"",H49/ABS(F49)) | J49: =IF(AND(ABS(H49)>Dashboard!$B$7,ISNUMBER(I49),ABS(I49)>Dashboard!$C$7),"FLAG","")
A50: ='TB_2026'!A18 | B50: ='TB_2026'!B18 | C50: ='TB_2026'!C18 | D50: Mar | E50: Apr | F50: ='TB_2026'!F18 | G50: ='TB_2026'!G18 | H50: =G50-F50 | I50: =IF(F50=0,"",H50/ABS(F50)) | J50: =IF(AND(ABS(H50)>Dashboard!$B$7,ISNUMBER(I50),ABS(I50)>Dashboard!$C$7),"FLAG","")
A51: ='TB_2026'!A19 | B51: ='TB_2026'!B19 | C51: ='TB_2026'!C19 | D51: Jan | E51: Feb | F51: ='TB_2026'!D19 | G51: ='TB_2026'!E19 | H51: =G51-F51 | I51: =IF(F51=0,"",H51/ABS(F51)) | J51: =IF(AND(ABS(H51)>Dashboard!$B$7,ISNUMBER(I51),ABS(I51)>Dashboard!$C$7),"FLAG","")
A52: ='TB_2026'!A19 | B52: ='TB_2026'!B19 | C52: ='TB_2026'!C19 | D52: Feb | E52: Mar | F52: ='TB_2026'!E19 | G52: ='TB_2026'!F19 | H52: =G52-F52 | I52: =IF(F52=0,"",H52/ABS(F52)) | J52: =IF(AND(ABS(H52)>Dashboard!$B$7,ISNUMBER(I52),ABS(I52)>Dashboard!$C$7),"FLAG","")
A53: ='TB_2026'!A19 | B53: ='TB_2026'!B19 | C53: ='TB_2026'!C19 | D53: Mar | E53: Apr | F53: ='TB_2026'!F19 | G53: ='TB_2026'!G19 | H53: =G53-F53 | I53: =IF(F53=0,"",H53/ABS(F53)) | J53: =IF(AND(ABS(H53)>Dashboard!$B$7,ISNUMBER(I53),ABS(I53)>Dashboard!$C$7),"FLAG","")
A54: ='TB_2026'!A20 | B54: ='TB_2026'!B20 | C54: ='TB_2026'!C20 | D54: Jan | E54: Feb | F54: ='TB_2026'!D20 | G54: ='TB_2026'!E20 | H54: =G54-F54 | I54: =IF(F54=0,"",H54/ABS(F54)) | J54: =IF(AND(ABS(H54)>Dashboard!$B$7,ISNUMBER(I54),ABS(I54)>Dashboard!$C$7),"FLAG","")
A55: ='TB_2026'!A20 | B55: ='TB_2026'!B20 | C55: ='TB_2026'!C20 | D55: Feb | E55: Mar | F55: ='TB_2026'!E20 | G55: ='TB_2026'!F20 | H55: =G55-F55 | I55: =IF(F55=0,"",H55/ABS(F55)) | J55: =IF(AND(ABS(H55)>Dashboard!$B$7,ISNUMBER(I55),ABS(I55)>Dashboard!$C$7),"FLAG","")
A56: ='TB_2026'!A20 | B56: ='TB_2026'!B20 | C56: ='TB_2026'!C20 | D56: Mar | E56: Apr | F56: ='TB_2026'!F20 | G56: ='TB_2026'!G20 | H56: =G56-F56 | I56: =IF(F56=0,"",H56/ABS(F56)) | J56: =IF(AND(ABS(H56)>Dashboard!$B$7,ISNUMBER(I56),ABS(I56)>Dashboard!$C$7),"FLAG","")
A57: ='TB_2026'!A21 | B57: ='TB_2026'!B21 | C57: ='TB_2026'!C21 | D57: Jan | E57: Feb | F57: ='TB_2026'!D21 | G57: ='TB_2026'!E21 | H57: =G57-F57 | I57: =IF(F57=0,"",H57/ABS(F57)) | J57: =IF(AND(ABS(H57)>Dashboard!$B$7,ISNUMBER(I57),ABS(I57)>Dashboard!$C$7),"FLAG","")
A58: ='TB_2026'!A21 | B58: ='TB_2026'!B21 | C58: ='TB_2026'!C21 | D58: Feb | E58: Mar | F58: ='TB_2026'!E21 | G58: ='TB_2026'!F21 | H58: =G58-F58 | I58: =IF(F58=0,"",H58/ABS(F58)) | J58: =IF(AND(ABS(H58)>Dashboard!$B$7,ISNUMBER(I58),ABS(I58)>Dashboard!$C$7),"FLAG","")
A59: ='TB_2026'!A21 | B59: ='TB_2026'!B21 | C59: ='TB_2026'!C21 | D59: Mar | E59: Apr | F59: ='TB_2026'!F21 | G59: ='TB_2026'!G21 | H59: =G59-F59 | I59: =IF(F59=0,"",H59/ABS(F59)) | J59: =IF(AND(ABS(H59)>Dashboard!$B$7,ISNUMBER(I59),ABS(I59)>Dashboard!$C$7),"FLAG","")
A60: ='TB_2026'!A22 | B60: ='TB_2026'!B22 | C60: ='TB_2026'!C22 | D60: Jan | E60: Feb | F60: ='TB_2026'!D22 | G60: ='TB_2026'!E22 | H60: =G60-F60 | I60: =IF(F60=0,"",H60/ABS(F60)) | J60: =IF(AND(ABS(H60)>Dashboard!$B$7,ISNUMBER(I60),ABS(I60)>Dashboard!$C$7),"FLAG","")
A61: ='TB_2026'!A22 | B61: ='TB_2026'!B22 | C61: ='TB_2026'!C22 | D61: Feb | E61: Mar | F61: ='TB_2026'!E22 | G61: ='TB_2026'!F22 | H61: =G61-F61 | I61: =IF(F61=0,"",H61/ABS(F61)) | J61: =IF(AND(ABS(H61)>Dashboard!$B$7,ISNUMBER(I61),ABS(I61)>Dashboard!$C$7),"FLAG","")
A62: ='TB_2026'!A22 | B62: ='TB_2026'!B22 | C62: ='TB_2026'!C22 | D62: Mar | E62: Apr | F62: ='TB_2026'!F22 | G62: ='TB_2026'!G22 | H62: =G62-F62 | I62: =IF(F62=0,"",H62/ABS(F62)) | J62: =IF(AND(ABS(H62)>Dashboard!$B$7,ISNUMBER(I62),ABS(I62)>Dashboard!$C$7),"FLAG","")
A63: ='TB_2026'!A23 | B63: ='TB_2026'!B23 | C63: ='TB_2026'!C23 | D63: Jan | E63: Feb | F63: ='TB_2026'!D23 | G63: ='TB_2026'!E23 | H63: =G63-F63 | I63: =IF(F63=0,"",H63/ABS(F63)) | J63: =IF(AND(ABS(H63)>Dashboard!$B$7,ISNUMBER(I63),ABS(I63)>Dashboard!$C$7),"FLAG","")
A64: ='TB_2026'!A23 | B64: ='TB_2026'!B23 | C64: ='TB_2026'!C23 | D64: Feb | E64: Mar | F64: ='TB_2026'!E23 | G64: ='TB_2026'!F23 | H64: =G64-F64 | I64: =IF(F64=0,"",H64/ABS(F64)) | J64: =IF(AND(ABS(H64)>Dashboard!$B$7,ISNUMBER(I64),ABS(I64)>Dashboard!$C$7),"FLAG","")
A65: ='TB_2026'!A23 | B65: ='TB_2026'!B23 | C65: ='TB_2026'!C23 | D65: Mar | E65: Apr | F65: ='TB_2026'!F23 | G65: ='TB_2026'!G23 | H65: =G65-F65 | I65: =IF(F65=0,"",H65/ABS(F65)) | J65: =IF(AND(ABS(H65)>Dashboard!$B$7,ISNUMBER(I65),ABS(I65)>Dashboard!$C$7),"FLAG","")
A66: ='TB_2026'!A24 | B66: ='TB_2026'!B24 | C66: ='TB_2026'!C24 | D66: Jan | E66: Feb | F66: ='TB_2026'!D24 | G66: ='TB_2026'!E24 | H66: =G66-F66 | I66: =IF(F66=0,"",H66/ABS(F66)) | J66: =IF(AND(ABS(H66)>Dashboard!$B$7,ISNUMBER(I66),ABS(I66)>Dashboard!$C$7),"FLAG","")
A67: ='TB_2026'!A24 | B67: ='TB_2026'!B24 | C67: ='TB_2026'!C24 | D67: Feb | E67: Mar | F67: ='TB_2026'!E24 | G67: ='TB_2026'!F24 | H67: =G67-F67 | I67: =IF(F67=0,"",H67/ABS(F67)) | J67: =IF(AND(ABS(H67)>Dashboard!$B$7,ISNUMBER(I67),ABS(I67)>Dashboard!$C$7),"FLAG","")
A68: ='TB_2026'!A24 | B68: ='TB_2026'!B24 | C68: ='TB_2026'!C24 | D68: Mar | E68: Apr | F68: ='TB_2026'!F24 | G68: ='TB_2026'!G24 | H68: =G68-F68 | I68: =IF(F68=0,"",H68/ABS(F68)) | J68: =IF(AND(ABS(H68)>Dashboard!$B$7,ISNUMBER(I68),ABS(I68)>Dashboard!$C$7),"FLAG","")
A69: ='TB_2026'!A25 | B69: ='TB_2026'!B25 | C69: ='TB_2026'!C25 | D69: Jan | E69: Feb | F69: ='TB_2026'!D25 | G69: ='TB_2026'!E25 | H69: =G69-F69 | I69: =IF(F69=0,"",H69/ABS(F69)) | J69: =IF(AND(ABS(H69)>Dashboard!$B$7,ISNUMBER(I69),ABS(I69)>Dashboard!$C$7),"FLAG","")
A70: ='TB_2026'!A25 | B70: ='TB_2026'!B25 | C70: ='TB_2026'!C25 | D70: Feb | E70: Mar | F70: ='TB_2026'!E25 | G70: ='TB_2026'!F25 | H70: =G70-F70 | I70: =IF(F70=0,"",H70/ABS(F70)) | J70: =IF(AND(ABS(H70)>Dashboard!$B$7,ISNUMBER(I70),ABS(I70)>Dashboard!$C$7),"FLAG","")
A71: ='TB_2026'!A25 | B71: ='TB_2026'!B25 | C71: ='TB_2026'!C25 | D71: Mar | E71: Apr | F71: ='TB_2026'!F25 | G71: ='TB_2026'!G25 | H71: =G71-F71 | I71: =IF(F71=0,"",H71/ABS(F71)) | J71: =IF(AND(ABS(H71)>Dashboard!$B$7,ISNUMBER(I71),ABS(I71)>Dashboard!$C$7),"FLAG","")
A72: ='TB_2026'!A26 | B72: ='TB_2026'!B26 | C72: ='TB_2026'!C26 | D72: Jan | E72: Feb | F72: ='TB_2026'!D26 | G72: ='TB_2026'!E26 | H72: =G72-F72 | I72: =IF(F72=0,"",H72/ABS(F72)) | J72: =IF(AND(ABS(H72)>Dashboard!$B$7,ISNUMBER(I72),ABS(I72)>Dashboard!$C$7),"FLAG","")
A73: ='TB_2026'!A26 | B73: ='TB_2026'!B26 | C73: ='TB_2026'!C26 | D73: Feb | E73: Mar | F73: ='TB_2026'!E26 | G73: ='TB_2026'!F26 | H73: =G73-F73 | I73: =IF(F73=0,"",H73/ABS(F73)) | J73: =IF(AND(ABS(H73)>Dashboard!$B$7,ISNUMBER(I73),ABS(I73)>Dashboard!$C$7),"FLAG","")
A74: ='TB_2026'!A26 | B74: ='TB_2026'!B26 | C74: ='TB_2026'!C26 | D74: Mar | E74: Apr | F74: ='TB_2026'!F26 | G74: ='TB_2026'!G26 | H74: =G74-F74 | I74: =IF(F74=0,"",H74/ABS(F74)) | J74: =IF(AND(ABS(H74)>Dashboard!$B$7,ISNUMBER(I74),ABS(I74)>Dashboard!$C$7),"FLAG","")
A75: ='TB_2026'!A27 | B75: ='TB_2026'!B27 | C75: ='TB_2026'!C27 | D75: Jan | E75: Feb | F75: ='TB_2026'!D27 | G75: ='TB_2026'!E27 | H75: =G75-F75 | I75: =IF(F75=0,"",H75/ABS(F75)) | J75: =IF(AND(ABS(H75)>Dashboard!$B$7,ISNUMBER(I75),ABS(I75)>Dashboard!$C$7),"FLAG","")
A76: ='TB_2026'!A27 | B76: ='TB_2026'!B27 | C76: ='TB_2026'!C27 | D76: Feb | E76: Mar | F76: ='TB_2026'!E27 | G76: ='TB_2026'!F27 | H76: =G76-F76 | I76: =IF(F76=0,"",H76/ABS(F76)) | J76: =IF(AND(ABS(H76)>Dashboard!$B$7,ISNUMBER(I76),ABS(I76)>Dashboard!$C$7),"FLAG","")
A77: ='TB_2026'!A27 | B77: ='TB_2026'!B27 | C77: ='TB_2026'!C27 | D77: Mar | E77: Apr | F77: ='TB_2026'!F27 | G77: ='TB_2026'!G27 | H77: =G77-F77 | I77: =IF(F77=0,"",H77/ABS(F77)) | J77: =IF(AND(ABS(H77)>Dashboard!$B$7,ISNUMBER(I77),ABS(I77)>Dashboard!$C$7),"FLAG","")
A78: ='TB_2026'!A28 | B78: ='TB_2026'!B28 | C78: ='TB_2026'!C28 | D78: Jan | E78: Feb | F78: ='TB_2026'!D28 | G78: ='TB_2026'!E28 | H78: =G78-F78 | I78: =IF(F78=0,"",H78/ABS(F78)) | J78: =IF(AND(ABS(H78)>Dashboard!$B$7,ISNUMBER(I78),ABS(I78)>Dashboard!$C$7),"FLAG","")
A79: ='TB_2026'!A28 | B79: ='TB_2026'!B28 | C79: ='TB_2026'!C28 | D79: Feb | E79: Mar | F79: ='TB_2026'!E28 | G79: ='TB_2026'!F28 | H79: =G79-F79 | I79: =IF(F79=0,"",H79/ABS(F79)) | J79: =IF(AND(ABS(H79)>Dashboard!$B$7,ISNUMBER(I79),ABS(I79)>Dashboard!$C$7),"FLAG","")
A80: ='TB_2026'!A28 | B80: ='TB_2026'!B28 | C80: ='TB_2026'!C28 | D80: Mar | E80: Apr | F80: ='TB_2026'!F28 | G80: ='TB_2026'!G28 | H80: =G80-F80 | I80: =IF(F80=0,"",H80/ABS(F80)) | J80: =IF(AND(ABS(H80)>Dashboard!$B$7,ISNUMBER(I80),ABS(I80)>Dashboard!$C$7),"FLAG","")
A81: ='TB_2026'!A29 | B81: ='TB_2026'!B29 | C81: ='TB_2026'!C29 | D81: Jan | E81: Feb | F81: ='TB_2026'!D29 | G81: ='TB_2026'!E29 | H81: =G81-F81 | I81: =IF(F81=0,"",H81/ABS(F81)) | J81: =IF(AND(ABS(H81)>Dashboard!$B$7,ISNUMBER(I81),ABS(I81)>Dashboard!$C$7),"FLAG","")
A82: ='TB_2026'!A29 | B82: ='TB_2026'!B29 | C82: ='TB_2026'!C29 | D82: Feb | E82: Mar | F82: ='TB_2026'!E29 | G82: ='TB_2026'!F29 | H82: =G82-F82 | I82: =IF(F82=0,"",H82/ABS(F82)) | J82: =IF(AND(ABS(H82)>Dashboard!$B$7,ISNUMBER(I82),ABS(I82)>Dashboard!$C$7),"FLAG","")
A83: ='TB_2026'!A29 | B83: ='TB_2026'!B29 | C83: ='TB_2026'!C29 | D83: Mar | E83: Apr | F83: ='TB_2026'!F29 | G83: ='TB_2026'!G29 | H83: =G83-F83 | I83: =IF(F83=0,"",H83/ABS(F83)) | J83: =IF(AND(ABS(H83)>Dashboard!$B$7,ISNUMBER(I83),ABS(I83)>Dashboard!$C$7),"FLAG","")
A84: ='TB_2026'!A30 | B84: ='TB_2026'!B30 | C84: ='TB_2026'!C30 | D84: Jan | E84: Feb | F84: ='TB_2026'!D30 | G84: ='TB_2026'!E30 | H84: =G84-F84 | I84: =IF(F84=0,"",H84/ABS(F84)) | J84: =IF(AND(ABS(H84)>Dashboard!$B$7,ISNUMBER(I84),ABS(I84)>Dashboard!$C$7),"FLAG","")
A85: ='TB_2026'!A30 | B85: ='TB_2026'!B30 | C85: ='TB_2026'!C30 | D85: Feb | E85: Mar | F85: ='TB_2026'!E30 | G85: ='TB_2026'!F30 | H85: =G85-F85 | I85: =IF(F85=0,"",H85/ABS(F85)) | J85: =IF(AND(ABS(H85)>Dashboard!$B$7,ISNUMBER(I85),ABS(I85)>Dashboard!$C$7),"FLAG","")
A86: ='TB_2026'!A30 | B86: ='TB_2026'!B30 | C86: ='TB_2026'!C30 | D86: Mar | E86: Apr | F86: ='TB_2026'!F30 | G86: ='TB_2026'!G30 | H86: =G86-F86 | I86: =IF(F86=0,"",H86/ABS(F86)) | J86: =IF(AND(ABS(H86)>Dashboard!$B$7,ISNUMBER(I86),ABS(I86)>Dashboard!$C$7),"FLAG","")
A87: ='TB_2026'!A31 | B87: ='TB_2026'!B31 | C87: ='TB_2026'!C31 | D87: Jan | E87: Feb | F87: ='TB_2026'!D31 | G87: ='TB_2026'!E31 | H87: =G87-F87 | I87: =IF(F87=0,"",H87/ABS(F87)) | J87: =IF(AND(ABS(H87)>Dashboard!$B$7,ISNUMBER(I87),ABS(I87)>Dashboard!$C$7),"FLAG","")
A88: ='TB_2026'!A31 | B88: ='TB_2026'!B31 | C88: ='TB_2026'!C31 | D88: Feb | E88: Mar | F88: ='TB_2026'!E31 | G88: ='TB_2026'!F31 | H88: =G88-F88 | I88: =IF(F88=0,"",H88/ABS(F88)) | J88: =IF(AND(ABS(H88)>Dashboard!$B$7,ISNUMBER(I88),ABS(I88)>Dashboard!$C$7),"FLAG","")
A89: ='TB_2026'!A31 | B89: ='TB_2026'!B31 | C89: ='TB_2026'!C31 | D89: Mar | E89: Apr | F89: ='TB_2026'!F31 | G89: ='TB_2026'!G31 | H89: =G89-F89 | I89: =IF(F89=0,"",H89/ABS(F89)) | J89: =IF(AND(ABS(H89)>Dashboard!$B$7,ISNUMBER(I89),ABS(I89)>Dashboard!$C$7),"FLAG","")
A90: ='TB_2026'!A32 | B90: ='TB_2026'!B32 | C90: ='TB_2026'!C32 | D90: Jan | E90: Feb | F90: ='TB_2026'!D32 | G90: ='TB_2026'!E32 | H90: =G90-F90 | I90: =IF(F90=0,"",H90/ABS(F90)) | J90: =IF(AND(ABS(H90)>Dashboard!$B$7,ISNUMBER(I90),ABS(I90)>Dashboard!$C$7),"FLAG","")
A91: ='TB_2026'!A32 | B91: ='TB_2026'!B32 | C91: ='TB_2026'!C32 | D91: Feb | E91: Mar | F91: ='TB_2026'!E32 | G91: ='TB_2026'!F32 | H91: =G91-F91 | I91: =IF(F91=0,"",H91/ABS(F91)) | J91: =IF(AND(ABS(H91)>Dashboard!$B$7,ISNUMBER(I91),ABS(I91)>Dashboard!$C$7),"FLAG","")
A92: ='TB_2026'!A32 | B92: ='TB_2026'!B32 | C92: ='TB_2026'!C32 | D92: Mar | E92: Apr | F92: ='TB_2026'!F32 | G92: ='TB_2026'!G32 | H92: =G92-F92 | I92: =IF(F92=0,"",H92/ABS(F92)) | J92: =IF(AND(ABS(H92)>Dashboard!$B$7,ISNUMBER(I92),ABS(I92)>Dashboard!$C$7),"FLAG","")
A93: ='TB_2026'!A33 | B93: ='TB_2026'!B33 | C93: ='TB_2026'!C33 | D93: Jan | E93: Feb | F93: ='TB_2026'!D33 | G93: ='TB_2026'!E33 | H93: =G93-F93 | I93: =IF(F93=0,"",H93/ABS(F93)) | J93: =IF(AND(ABS(H93)>Dashboard!$B$7,ISNUMBER(I93),ABS(I93)>Dashboard!$C$7),"FLAG","")
A94: ='TB_2026'!A33 | B94: ='TB_2026'!B33 | C94: ='TB_2026'!C33 | D94: Feb | E94: Mar | F94: ='TB_2026'!E33 | G94: ='TB_2026'!F33 | H94: =G94-F94 | I94: =IF(F94=0,"",H94/ABS(F94)) | J94: =IF(AND(ABS(H94)>Dashboard!$B$7,ISNUMBER(I94),ABS(I94)>Dashboard!$C$7),"FLAG","")
A95: ='TB_2026'!A33 | B95: ='TB_2026'!B33 | C95: ='TB_2026'!C33 | D95: Mar | E95: Apr | F95: ='TB_2026'!F33 | G95: ='TB_2026'!G33 | H95: =G95-F95 | I95: =IF(F95=0,"",H95/ABS(F95)) | J95: =IF(AND(ABS(H95)>Dashboard!$B$7,ISNUMBER(I95),ABS(I95)>Dashboard!$C$7),"FLAG","")
A96: ='TB_2026'!A34 | B96: ='TB_2026'!B34 | C96: ='TB_2026'!C34 | D96: Jan | E96: Feb | F96: ='TB_2026'!D34 | G96: ='TB_2026'!E34 | H96: =G96-F96 | I96: =IF(F96=0,"",H96/ABS(F96)) | J96: =IF(AND(ABS(H96)>Dashboard!$B$7,ISNUMBER(I96),ABS(I96)>Dashboard!$C$7),"FLAG","")
A97: ='TB_2026'!A34 | B97: ='TB_2026'!B34 | C97: ='TB_2026'!C34 | D97: Feb | E97: Mar | F97: ='TB_2026'!E34 | G97: ='TB_2026'!F34 | H97: =G97-F97 | I97: =IF(F97=0,"",H97/ABS(F97)) | J97: =IF(AND(ABS(H97)>Dashboard!$B$7,ISNUMBER(I97),ABS(I97)>Dashboard!$C$7),"FLAG","")
A98: ='TB_2026'!A34 | B98: ='TB_2026'!B34 | C98: ='TB_2026'!C34 | D98: Mar | E98: Apr | F98: ='TB_2026'!F34 | G98: ='TB_2026'!G34 | H98: =G98-F98 | I98: =IF(F98=0,"",H98/ABS(F98)) | J98: =IF(AND(ABS(H98)>Dashboard!$B$7,ISNUMBER(I98),ABS(I98)>Dashboard!$C$7),"FLAG","")

Sheet Flagged_Summary
A1: Flagged Accounts - every cell below traces to YoY_Variance / MoM_Variance
A2: Type | B2: Account | C2: Period | D2: $ Var | E2: % Var | F2: Note
A3: YoY | B3: =YoY_Variance!B3 | C3: =YoY_Variance!D3 | D3: =YoY_Variance!G3 | E3: =YoY_Variance!H3
A4: YoY | B4: =YoY_Variance!B4 | C4: =YoY_Variance!D4 | D4: =YoY_Variance!G4 | E4: =YoY_Variance!H4
A5: YoY | B5: =YoY_Variance!B5 | C5: =YoY_Variance!D5 | D5: =YoY_Variance!G5 | E5: =YoY_Variance!H5
A6: YoY | B6: =YoY_Variance!B6 | C6: =YoY_Variance!D6 | D6: =YoY_Variance!G6 | E6: =YoY_Variance!H6
A7: YoY | B7: =YoY_Variance!B14 | C7: =YoY_Variance!D14 | D7: =YoY_Variance!G14 | E7: =YoY_Variance!H14 | F7: Balloons in April 2026 specifically - invisible in a single month, obvious once diffed.
A8: YoY | B8: =YoY_Variance!B31 | C8: =YoY_Variance!D31 | D8: =YoY_Variance!G31 | E8: =YoY_Variance!H31
A9: YoY | B9: =YoY_Variance!B32 | C9: =YoY_Variance!D32 | D9: =YoY_Variance!G32 | E9: =YoY_Variance!H32
A10: YoY | B10: =YoY_Variance!B33 | C10: =YoY_Variance!D33 | D10: =YoY_Variance!G33 | E10: =YoY_Variance!H33
A11: YoY | B11: =YoY_Variance!B34 | C11: =YoY_Variance!D34 | D11: =YoY_Variance!G34 | E11: =YoY_Variance!H34
A12: YoY | B12: =YoY_Variance!B59 | C12: =YoY_Variance!D59 | D12: =YoY_Variance!G59 | E12: =YoY_Variance!H59
A13: YoY | B13: =YoY_Variance!B60 | C13: =YoY_Variance!D60 | D13: =YoY_Variance!G60 | E13: =YoY_Variance!H60
A14: YoY | B14: =YoY_Variance!B61 | C14: =YoY_Variance!D61 | D14: =YoY_Variance!G61 | E14: =YoY_Variance!H61
A15: YoY | B15: =YoY_Variance!B62 | C15: =YoY_Variance!D62 | D15: =YoY_Variance!G62 | E15: =YoY_Variance!H62
A16: YoY | B16: =YoY_Variance!B70 | C16: =YoY_Variance!D70 | D16: =YoY_Variance!G70 | E16: =YoY_Variance!H70
A17: YoY | B17: =YoY_Variance!B85 | C17: =YoY_Variance!D85 | D17: =YoY_Variance!G85 | E17: =YoY_Variance!H85 | F17: Consistent with vendor cost inflation noted in Article 01 - dated and quantified here.
A18: YoY | B18: =YoY_Variance!B86 | C18: =YoY_Variance!D86 | D18: =YoY_Variance!G86 | E18: =YoY_Variance!H86 | F18: Consistent with vendor cost inflation noted in Article 01 - dated and quantified here.
A19: YoY | B19: =YoY_Variance!B105 | C19: =YoY_Variance!D105 | D19: =YoY_Variance!G105 | E19: =YoY_Variance!H105 | F19: One-month spike, not present in the prior year at all - real campaign or miscoded invoice?
A20: MoM | B20: =MoM_Variance!B11 | C20: =MoM_Variance!D11&"->"&MoM_Variance!E11 | D20: =MoM_Variance!H11 | E20: =MoM_Variance!I11 | F20: Balloons in April 2026 specifically - invisible in a single month, obvious once diffed.
A21: MoM | B21: =MoM_Variance!B53 | C21: =MoM_Variance!D53&"->"&MoM_Variance!E53 | D21: =MoM_Variance!H53 | E21: =MoM_Variance!I53
A22: MoM | B22: =MoM_Variance!B64 | C22: =MoM_Variance!D64&"->"&MoM_Variance!E64 | D22: =MoM_Variance!H64 | E22: =MoM_Variance!I64
A23: MoM | B23: =MoM_Variance!B79 | C23: =MoM_Variance!D79&"->"&MoM_Variance!E79 | D23: =MoM_Variance!H79 | E23: =MoM_Variance!I79 | F23: One-month spike, not present in the prior year at all - real campaign or miscoded invoice?
A24: MoM | B24: =MoM_Variance!B80 | C24: =MoM_Variance!D80&"->"&MoM_Variance!E80 | D24: =MoM_Variance!H80 | E24: =MoM_Variance!I80 | F24: One-month spike, not present in the prior year at all - real campaign or miscoded invoice?
A25: MoM | B25: =MoM_Variance!B87 | C25: =MoM_Variance!D87&"->"&MoM_Variance!E87 | D25: =MoM_Variance!H87 | E25: =MoM_Variance!I87 | F25: Recurring seasonal pattern - same February spike both years. Not a surprise; flagged here because MoM measures sequential movement, not because it's new.
A26: MoM | B26: =MoM_Variance!B88 | C26: =MoM_Variance!D88&"->"&MoM_Variance!E88 | D26: =MoM_Variance!H88 | E26: =MoM_Variance!I88 | F26: Recurring seasonal pattern - same February spike both years. Not a surprise; flagged here because MoM measures sequential movement, not because it's new.
